{"station_id": "GDN_01", "count": 200, "records": [{"timestamp": "2026-06-12T13:25:11.055945+00:00", "station_id": "GDN_01", "temperature": 13.01, "humidity": 49.46, "pressure": 1012.45, "wind_speed": 2.85, "wind_direction": 196, "rain_mm": 0, "cloud_cover": 54}, {"timestamp": "2026-06-12T13:15:11.055945+00:00", "station_id": "GDN_01", "temperature": 18.72, "humidity": 59.07, "pressure": 996.06, "wind_speed": 4.41, "wind_direction": 353, "rain_mm": 1.17, "cloud_cover": 22}, {"timestamp": "2026-06-12T13:05:11.055945+00:00", "station_id": "GDN_01", "temperature": 15.58, "humidity": 59.25, "pressure": 1010.53, "wind_speed": 2.48, "wind_direction": 83, "rain_mm": 0.17, "cloud_cover": 99}, {"timestamp": "2026-06-12T12:55:11.055945+00:00", "station_id": "GDN_01", "temperature": 16.16, "humidity": 63.9, "pressure": 1025.52, "wind_speed": 13.32, "wind_direction": 132, "rain_mm": 1.03, "cloud_cover": 2}, {"timestamp": "2026-06-12T12:45:11.055945+00:00", "station_id": "GDN_01", "temperature": 20.66, "humidity": 47.65, "pressure": 1030.0, "wind_speed": 7.51, "wind_direction": 33, "rain_mm": 1.34, "cloud_cover": 9}, {"timestamp": "2026-06-12T12:35:11.055945+00:00", "station_id": "GDN_01", "temperature": 17.72, "humidity": 67.63, "pressure": 1004.22, "wind_speed": 8.42, "wind_direction": 274, "rain_mm": 0.72, "cloud_cover": 22}, {"timestamp": "2026-06-12T12:25:11.055945+00:00", "station_id": "GDN_01", "temperature": 16.24, "humidity": 47.68, "pressure": 1003.07, "wind_speed": 8.38, "wind_direction": 336, "rain_mm": 0.57, "cloud_cover": 4}, {"timestamp": "2026-06-12T12:15:11.055945+00:00", "station_id": "GDN_01", "temperature": 16.06, "humidity": 58.9, "pressure": 1028.67, "wind_speed": 3.94, "wind_direction": 43, "rain_mm": 0, "cloud_cover": 24}, {"timestamp": "2026-06-12T12:05:11.055945+00:00", "station_id": "GDN_01", "temperature": 13.87, "humidity": 92.34, "pressure": 1025.85, "wind_speed": 10.43, "wind_direction": 336, "rain_mm": 0, "cloud_cover": 45}, {"timestamp": "2026-06-12T11:55:11.055945+00:00", "station_id": "GDN_01", "temperature": 15.98, "humidity": 76.65, "pressure": 1007.72, "wind_speed": 8.68, "wind_direction": 40, "rain_mm": 0.17, "cloud_cover": 16}, {"timestamp": "2026-06-12T11:45:11.055945+00:00", "station_id": "GDN_01", "temperature": 15.74, "humidity": 76.63, "pressure": 1022.01, "wind_speed": 8.56, "wind_direction": 129, "rain_mm": 0, "cloud_cover": 21}, {"timestamp": "2026-06-12T11:35:11.055945+00:00", "station_id": "GDN_01", "temperature": 17.03, "humidity": 73.65, "pressure": 1003.88, "wind_speed": 13.05, "wind_direction": 146, "rain_mm": 0, "cloud_cover": 35}, {"timestamp": "2026-06-12T11:25:11.055945+00:00", "station_id": "GDN_01", "temperature": 15.78, "humidity": 66.18, "pressure": 1008.15, "wind_speed": 6.81, "wind_direction": 270, "rain_mm": 0, "cloud_cover": 38}, {"timestamp": "2026-06-12T11:15:11.055945+00:00", "station_id": "GDN_01", "temperature": 17.74, "humidity": 72.12, "pressure": 996.1, "wind_speed": 5.04, "wind_direction": 140, "rain_mm": 0.49, "cloud_cover": 8}, {"timestamp": "2026-06-12T11:05:11.055945+00:00", "station_id": "GDN_01", "temperature": 13.2, "humidity": 74.1, "pressure": 1027.68, "wind_speed": 12.39, "wind_direction": 260, "rain_mm": 1.23, "cloud_cover": 74}, {"timestamp": "2026-06-12T10:55:11.055945+00:00", "station_id": "GDN_01", "temperature": 19.97, "humidity": 45.49, "pressure": 1007.78, "wind_speed": 10.38, "wind_direction": 190, "rain_mm": 0, "cloud_cover": 90}, {"timestamp": "2026-06-12T10:45:11.055945+00:00", "station_id": "GDN_01", "temperature": 16.72, "humidity": 62.92, "pressure": 998.43, "wind_speed": 4.46, "wind_direction": 343, "rain_mm": 0, "cloud_cover": 15}, {"timestamp": "2026-06-12T10:35:11.055945+00:00", "station_id": "GDN_01", "temperature": 16.0, "humidity": 89.51, "pressure": 1007.3, "wind_speed": 11.4, "wind_direction": 63, "rain_mm": 0, "cloud_cover": 49}, {"timestamp": "2026-06-12T10:25:11.055945+00:00", "station_id": "GDN_01", "temperature": 13.31, "humidity": 93.36, "pressure": 1003.35, "wind_speed": 9.55, "wind_direction": 259, "rain_mm": 0.89, "cloud_cover": 34}, {"timestamp": "2026-06-12T10:15:11.055945+00:00", "station_id": "GDN_01", "temperature": 17.27, "humidity": 64.35, "pressure": 1009.48, "wind_speed": 10.37, "wind_direction": 330, "rain_mm": 1.61, "cloud_cover": 62}, {"timestamp": "2026-06-12T10:05:11.055945+00:00", "station_id": "GDN_01", "temperature": 20.36, "humidity": 55.48, "pressure": 1001.28, "wind_speed": 4.92, "wind_direction": 341, "rain_mm": 0, "cloud_cover": 75}, {"timestamp": "2026-06-12T09:55:11.055945+00:00", "station_id": "GDN_01", "temperature": 16.92, "humidity": 70.74, "pressure": 1008.14, "wind_speed": 7.65, "wind_direction": 346, "rain_mm": 0.28, "cloud_cover": 41}, {"timestamp": "2026-06-12T09:45:11.055945+00:00", "station_id": "GDN_01", "temperature": 20.48, "humidity": 58.84, "pressure": 1020.1, "wind_speed": 4.51, "wind_direction": 298, "rain_mm": 0, "cloud_cover": 23}, {"timestamp": "2026-06-12T09:35:11.055945+00:00", "station_id": "GDN_01", "temperature": 15.76, "humidity": 59.37, "pressure": 999.19, "wind_speed": 1.11, "wind_direction": 308, "rain_mm": 0.2, "cloud_cover": 49}, {"timestamp": "2026-06-12T09:25:11.055945+00:00", "station_id": "GDN_01", "temperature": 14.46, "humidity": 53.43, "pressure": 1019.53, "wind_speed": 10.43, "wind_direction": 148, "rain_mm": 1.34, "cloud_cover": 70}, {"timestamp": "2026-06-12T09:15:11.055945+00:00", "station_id": "GDN_01", "temperature": 20.86, "humidity": 50.54, "pressure": 1006.2, "wind_speed": 13.3, "wind_direction": 155, "rain_mm": 0, "cloud_cover": 95}, {"timestamp": "2026-06-12T09:05:11.055945+00:00", "station_id": "GDN_01", "temperature": 13.64, "humidity": 83.23, "pressure": 1015.38, "wind_speed": 4.04, "wind_direction": 96, "rain_mm": 0.31, "cloud_cover": 91}, {"timestamp": "2026-06-12T08:55:11.055945+00:00", "station_id": "GDN_01", "temperature": 17.09, "humidity": 85.76, "pressure": 1004.13, "wind_speed": 13.88, "wind_direction": 282, "rain_mm": 2.41, "cloud_cover": 49}, {"timestamp": "2026-06-12T08:45:11.055945+00:00", "station_id": "GDN_01", "temperature": 13.71, "humidity": 46.08, "pressure": 1014.34, "wind_speed": 4.09, "wind_direction": 238, "rain_mm": 1.01, "cloud_cover": 94}, {"timestamp": "2026-06-12T08:35:11.055945+00:00", "station_id": "GDN_01", "temperature": 20.25, "humidity": 68.84, "pressure": 996.51, "wind_speed": 5.64, "wind_direction": 205, "rain_mm": 1.2, "cloud_cover": 46}, {"timestamp": "2026-06-12T08:25:11.055945+00:00", "station_id": "GDN_01", "temperature": 14.31, "humidity": 54.04, "pressure": 1020.31, "wind_speed": 12.03, "wind_direction": 251, "rain_mm": 1.21, "cloud_cover": 68}, {"timestamp": "2026-06-12T08:15:11.055945+00:00", "station_id": "GDN_01", "temperature": 18.09, "humidity": 93.9, "pressure": 1007.11, "wind_speed": 7.15, "wind_direction": 105, "rain_mm": 0, "cloud_cover": 65}, {"timestamp": "2026-06-12T08:05:11.055945+00:00", "station_id": "GDN_01", "temperature": 13.65, "humidity": 74.01, "pressure": 1016.81, "wind_speed": 2.98, "wind_direction": 8, "rain_mm": 1.17, "cloud_cover": 8}, {"timestamp": "2026-06-12T07:55:11.055945+00:00", "station_id": "GDN_01", "temperature": 17.19, "humidity": 45.45, "pressure": 1019.38, "wind_speed": 5.89, "wind_direction": 240, "rain_mm": 1.42, "cloud_cover": 10}, {"timestamp": "2026-06-12T07:45:11.055945+00:00", "station_id": "GDN_01", "temperature": 19.91, "humidity": 55.03, "pressure": 996.42, "wind_speed": 5.66, "wind_direction": 158, "rain_mm": 0.14, "cloud_cover": 76}, {"timestamp": "2026-06-12T07:35:11.055945+00:00", "station_id": "GDN_01", "temperature": 16.27, "humidity": 88.83, "pressure": 997.33, "wind_speed": 3.73, "wind_direction": 276, "rain_mm": 0.21, "cloud_cover": 58}, {"timestamp": "2026-06-12T07:25:11.055945+00:00", "station_id": "GDN_01", "temperature": 14.55, "humidity": 66.32, "pressure": 998.92, "wind_speed": 5.38, "wind_direction": 141, "rain_mm": 1.16, "cloud_cover": 10}, {"timestamp": "2026-06-12T07:15:11.055945+00:00", "station_id": "GDN_01", "temperature": 17.16, "humidity": 48.18, "pressure": 1016.35, "wind_speed": 11.22, "wind_direction": 109, "rain_mm": 0.68, "cloud_cover": 80}, {"timestamp": "2026-06-12T07:05:11.055945+00:00", "station_id": "GDN_01", "temperature": 14.52, "humidity": 89.66, "pressure": 1000.01, "wind_speed": 2.17, "wind_direction": 38, "rain_mm": 0.57, "cloud_cover": 37}, {"timestamp": "2026-06-12T06:55:11.055945+00:00", "station_id": "GDN_01", "temperature": 13.08, "humidity": 75.97, "pressure": 1014.04, "wind_speed": 2.24, "wind_direction": 305, "rain_mm": 0.9, "cloud_cover": 66}, {"timestamp": "2026-06-12T06:45:11.055945+00:00", "station_id": "GDN_01", "temperature": 18.17, "humidity": 68.87, "pressure": 1011.4, "wind_speed": 8.86, "wind_direction": 184, "rain_mm": 0.26, "cloud_cover": 2}, {"timestamp": "2026-06-12T06:35:11.055945+00:00", "station_id": "GDN_01", "temperature": 13.22, "humidity": 61.22, "pressure": 1027.64, "wind_speed": 5.39, "wind_direction": 152, "rain_mm": 0.1, "cloud_cover": 93}, {"timestamp": "2026-06-12T06:25:11.055945+00:00", "station_id": "GDN_01", "temperature": 14.96, "humidity": 92.44, "pressure": 998.75, "wind_speed": 3.68, "wind_direction": 331, "rain_mm": 0, "cloud_cover": 52}, {"timestamp": "2026-06-12T06:15:11.055945+00:00", "station_id": "GDN_01", "temperature": 20.09, "humidity": 86.92, "pressure": 1009.78, "wind_speed": 0.09, "wind_direction": 164, "rain_mm": 1.38, "cloud_cover": 60}, {"timestamp": "2026-06-12T06:05:11.055945+00:00", "station_id": "GDN_01", "temperature": 18.4, "humidity": 65.6, "pressure": 995.06, "wind_speed": 9.9, "wind_direction": 324, "rain_mm": 1.01, "cloud_cover": 16}, {"timestamp": "2026-06-12T05:55:11.055945+00:00", "station_id": "GDN_01", "temperature": 18.05, "humidity": 67.36, "pressure": 1006.56, "wind_speed": 11.07, "wind_direction": 325, "rain_mm": 1.58, "cloud_cover": 98}, {"timestamp": "2026-06-12T05:45:11.055945+00:00", "station_id": "GDN_01", "temperature": 19.44, "humidity": 60.41, "pressure": 1009.13, "wind_speed": 2.59, "wind_direction": 198, "rain_mm": 1.15, "cloud_cover": 87}, {"timestamp": "2026-06-12T05:35:11.055945+00:00", "station_id": "GDN_01", "temperature": 13.67, "humidity": 79.85, "pressure": 1003.34, "wind_speed": 1.13, "wind_direction": 194, "rain_mm": 0, "cloud_cover": 15}, {"timestamp": "2026-06-12T05:25:11.055945+00:00", "station_id": "GDN_01", "temperature": 19.45, "humidity": 52.25, "pressure": 1017.35, "wind_speed": 13.62, "wind_direction": 343, "rain_mm": 0.27, "cloud_cover": 0}, {"timestamp": "2026-06-12T05:15:11.055945+00:00", "station_id": "GDN_01", "temperature": 15.08, "humidity": 46.01, "pressure": 1018.59, "wind_speed": 7.34, "wind_direction": 179, "rain_mm": 0, "cloud_cover": 65}, {"timestamp": "2026-06-12T05:05:11.055945+00:00", "station_id": "GDN_01", "temperature": 14.55, "humidity": 87.44, "pressure": 1017.27, "wind_speed": 1.37, "wind_direction": 35, "rain_mm": 0.29, "cloud_cover": 0}, {"timestamp": "2026-06-12T04:55:11.055945+00:00", "station_id": "GDN_01", "temperature": 15.82, "humidity": 78.2, "pressure": 1026.66, "wind_speed": 6.11, "wind_direction": 267, "rain_mm": 0.17, "cloud_cover": 93}, {"timestamp": "2026-06-12T04:45:11.055945+00:00", "station_id": "GDN_01", "temperature": 15.58, "humidity": 70.02, "pressure": 1017.82, "wind_speed": 1.7, "wind_direction": 95, "rain_mm": 0.64, "cloud_cover": 72}, {"timestamp": "2026-06-12T04:35:11.055945+00:00", "station_id": "GDN_01", "temperature": 18.16, "humidity": 81.56, "pressure": 1015.48, "wind_speed": 0.57, "wind_direction": 2, "rain_mm": 0, "cloud_cover": 98}, {"timestamp": "2026-06-12T04:25:11.055945+00:00", "station_id": "GDN_01", "temperature": 20.43, "humidity": 88.28, "pressure": 1026.4, "wind_speed": 2.0, "wind_direction": 129, "rain_mm": 1.36, "cloud_cover": 38}, {"timestamp": "2026-06-12T04:15:11.055945+00:00", "station_id": "GDN_01", "temperature": 15.4, "humidity": 63.46, "pressure": 1012.94, "wind_speed": 8.09, "wind_direction": 180, "rain_mm": 0, "cloud_cover": 23}, {"timestamp": "2026-06-12T04:05:11.055945+00:00", "station_id": "GDN_01", "temperature": 14.03, "humidity": 74.65, "pressure": 1021.13, "wind_speed": 9.9, "wind_direction": 12, "rain_mm": 0.18, "cloud_cover": 2}, {"timestamp": "2026-06-12T03:55:11.055945+00:00", "station_id": "GDN_01", "temperature": 14.72, "humidity": 61.09, "pressure": 1024.64, "wind_speed": 12.34, "wind_direction": 36, "rain_mm": 0.19, "cloud_cover": 100}, {"timestamp": "2026-06-12T03:45:11.055945+00:00", "station_id": "GDN_01", "temperature": 14.43, "humidity": 76.72, "pressure": 1024.88, "wind_speed": 6.44, "wind_direction": 34, "rain_mm": 0.87, "cloud_cover": 36}, {"timestamp": "2026-06-12T03:35:11.055945+00:00", "station_id": "GDN_01", "temperature": 16.51, "humidity": 82.91, "pressure": 1019.63, "wind_speed": 9.07, "wind_direction": 325, "rain_mm": 0.22, "cloud_cover": 39}, {"timestamp": "2026-06-12T03:25:11.055945+00:00", "station_id": "GDN_01", "temperature": 18.5, "humidity": 88.96, "pressure": 1004.64, "wind_speed": 0.59, "wind_direction": 220, "rain_mm": 1.45, "cloud_cover": 19}, {"timestamp": "2026-06-12T03:15:11.055945+00:00", "station_id": "GDN_01", "temperature": 17.19, "humidity": 66.18, "pressure": 998.41, "wind_speed": 7.66, "wind_direction": 64, "rain_mm": 0, "cloud_cover": 100}, {"timestamp": "2026-06-12T03:05:11.055945+00:00", "station_id": "GDN_01", "temperature": 18.57, "humidity": 75.16, "pressure": 995.32, "wind_speed": 5.37, "wind_direction": 104, "rain_mm": 1.14, "cloud_cover": 63}, {"timestamp": "2026-06-12T02:55:11.055945+00:00", "station_id": "GDN_01", "temperature": 15.03, "humidity": 94.13, "pressure": 1020.23, "wind_speed": 2.65, "wind_direction": 102, "rain_mm": 0.68, "cloud_cover": 82}, {"timestamp": "2026-06-12T02:45:11.055945+00:00", "station_id": "GDN_01", "temperature": 15.93, "humidity": 71.59, "pressure": 996.36, "wind_speed": 5.77, "wind_direction": 276, "rain_mm": 0.28, "cloud_cover": 43}, {"timestamp": "2026-06-12T02:35:11.055945+00:00", "station_id": "GDN_01", "temperature": 16.0, "humidity": 87.41, "pressure": 1019.87, "wind_speed": 10.14, "wind_direction": 25, "rain_mm": 0.03, "cloud_cover": 9}, {"timestamp": "2026-06-12T02:25:11.055945+00:00", "station_id": "GDN_01", "temperature": 20.6, "humidity": 76.76, "pressure": 1010.04, "wind_speed": 3.35, "wind_direction": 156, "rain_mm": 1.95, "cloud_cover": 64}, {"timestamp": "2026-06-12T02:15:11.055945+00:00", "station_id": "GDN_01", "temperature": 17.01, "humidity": 85.39, "pressure": 1027.21, "wind_speed": 2.71, "wind_direction": 231, "rain_mm": 1.07, "cloud_cover": 91}, {"timestamp": "2026-06-12T02:05:11.055945+00:00", "station_id": "GDN_01", "temperature": 20.97, "humidity": 46.73, "pressure": 995.75, "wind_speed": 0.57, "wind_direction": 255, "rain_mm": 0, "cloud_cover": 24}, {"timestamp": "2026-06-12T01:55:11.055945+00:00", "station_id": "GDN_01", "temperature": 13.19, "humidity": 61.04, "pressure": 1001.53, "wind_speed": 11.0, "wind_direction": 15, "rain_mm": 0, "cloud_cover": 18}, {"timestamp": "2026-06-12T01:45:11.055945+00:00", "station_id": "GDN_01", "temperature": 19.64, "humidity": 49.34, "pressure": 1002.72, "wind_speed": 0.38, "wind_direction": 312, "rain_mm": 1.01, "cloud_cover": 97}, {"timestamp": "2026-06-12T01:35:11.055945+00:00", "station_id": "GDN_01", "temperature": 14.14, "humidity": 67.35, "pressure": 1027.49, "wind_speed": 10.43, "wind_direction": 144, "rain_mm": 0, "cloud_cover": 61}, {"timestamp": "2026-06-12T01:25:11.055945+00:00", "station_id": "GDN_01", "temperature": 20.2, "humidity": 80.42, "pressure": 1019.21, "wind_speed": 6.22, "wind_direction": 292, "rain_mm": 0.27, "cloud_cover": 32}, {"timestamp": "2026-06-12T01:15:11.055945+00:00", "station_id": "GDN_01", "temperature": 20.08, "humidity": 54.53, "pressure": 1023.86, "wind_speed": 12.75, "wind_direction": 277, "rain_mm": 0, "cloud_cover": 20}, {"timestamp": "2026-06-12T01:05:11.055945+00:00", "station_id": "GDN_01", "temperature": 17.52, "humidity": 48.64, "pressure": 1003.8, "wind_speed": 13.76, "wind_direction": 76, "rain_mm": 0, "cloud_cover": 76}, {"timestamp": "2026-06-12T00:55:11.055945+00:00", "station_id": "GDN_01", "temperature": 18.66, "humidity": 94.66, "pressure": 1016.94, "wind_speed": 9.65, "wind_direction": 169, "rain_mm": 0, "cloud_cover": 75}, {"timestamp": "2026-06-12T00:45:11.055945+00:00", "station_id": "GDN_01", "temperature": 15.69, "humidity": 74.8, "pressure": 1006.33, "wind_speed": 13.28, "wind_direction": 225, "rain_mm": 0, "cloud_cover": 41}, {"timestamp": "2026-06-12T00:35:11.055945+00:00", "station_id": "GDN_01", "temperature": 15.56, "humidity": 63.83, "pressure": 997.96, "wind_speed": 10.3, "wind_direction": 102, "rain_mm": 0.94, "cloud_cover": 64}, {"timestamp": "2026-06-12T00:25:11.055945+00:00", "station_id": "GDN_01", "temperature": 13.1, "humidity": 65.16, "pressure": 1020.66, "wind_speed": 4.82, "wind_direction": 6, "rain_mm": 0.41, "cloud_cover": 66}, {"timestamp": "2026-06-12T00:15:11.055945+00:00", "station_id": "GDN_01", "temperature": 17.3, "humidity": 49.92, "pressure": 1028.16, "wind_speed": 7.03, "wind_direction": 319, "rain_mm": 0, "cloud_cover": 64}, {"timestamp": "2026-06-12T00:05:11.055945+00:00", "station_id": "GDN_01", "temperature": 17.15, "humidity": 70.34, "pressure": 1011.0, "wind_speed": 5.24, "wind_direction": 83, "rain_mm": 0.04, "cloud_cover": 33}, {"timestamp": "2026-06-11T23:55:11.055945+00:00", "station_id": "GDN_01", "temperature": 15.96, "humidity": 80.46, "pressure": 1028.86, "wind_speed": 9.31, "wind_direction": 54, "rain_mm": 0, "cloud_cover": 28}, {"timestamp": "2026-06-11T23:45:11.055945+00:00", "station_id": "GDN_01", "temperature": 18.86, "humidity": 65.63, "pressure": 1022.52, "wind_speed": 13.37, "wind_direction": 273, "rain_mm": 0.86, "cloud_cover": 16}, {"timestamp": "2026-06-11T23:35:11.055945+00:00", "station_id": "GDN_01", "temperature": 18.23, "humidity": 75.44, "pressure": 1006.37, "wind_speed": 4.32, "wind_direction": 146, "rain_mm": 1.95, "cloud_cover": 41}, {"timestamp": "2026-06-11T23:25:11.055945+00:00", "station_id": "GDN_01", "temperature": 14.68, "humidity": 71.78, "pressure": 1013.54, "wind_speed": 10.38, "wind_direction": 144, "rain_mm": 0, "cloud_cover": 54}, {"timestamp": "2026-06-11T23:15:11.055945+00:00", "station_id": "GDN_01", "temperature": 14.36, "humidity": 80.5, "pressure": 1001.23, "wind_speed": 11.95, "wind_direction": 98, "rain_mm": 0.44, "cloud_cover": 72}, {"timestamp": "2026-06-11T23:05:11.055945+00:00", "station_id": "GDN_01", "temperature": 13.15, "humidity": 56.93, "pressure": 1000.02, "wind_speed": 8.67, "wind_direction": 202, "rain_mm": 0, "cloud_cover": 54}, {"timestamp": "2026-06-11T22:55:11.055945+00:00", "station_id": "GDN_01", "temperature": 15.4, "humidity": 49.34, "pressure": 1011.69, "wind_speed": 9.81, "wind_direction": 74, "rain_mm": 0, "cloud_cover": 64}, {"timestamp": "2026-06-11T22:45:11.055945+00:00", "station_id": "GDN_01", "temperature": 15.69, "humidity": 85.13, "pressure": 1022.35, "wind_speed": 10.49, "wind_direction": 113, "rain_mm": 1.67, "cloud_cover": 56}, {"timestamp": "2026-06-11T22:35:11.055945+00:00", "station_id": "GDN_01", "temperature": 13.16, "humidity": 69.39, "pressure": 1006.95, "wind_speed": 11.83, "wind_direction": 227, "rain_mm": 0.93, "cloud_cover": 40}, {"timestamp": "2026-06-11T22:25:11.055945+00:00", "station_id": "GDN_01", "temperature": 15.99, "humidity": 56.82, "pressure": 1012.78, "wind_speed": 5.38, "wind_direction": 127, "rain_mm": 1.56, "cloud_cover": 5}, {"timestamp": "2026-06-11T22:15:11.055945+00:00", "station_id": "GDN_01", "temperature": 18.84, "humidity": 83.01, "pressure": 996.05, "wind_speed": 5.49, "wind_direction": 238, "rain_mm": 0.36, "cloud_cover": 23}, {"timestamp": "2026-06-11T22:05:11.055945+00:00", "station_id": "GDN_01", "temperature": 16.17, "humidity": 61.72, "pressure": 1022.57, "wind_speed": 11.6, "wind_direction": 86, "rain_mm": 0.03, "cloud_cover": 13}, {"timestamp": "2026-06-11T21:55:11.055945+00:00", "station_id": "GDN_01", "temperature": 16.43, "humidity": 87.87, "pressure": 1020.53, "wind_speed": 4.25, "wind_direction": 295, "rain_mm": 0.81, "cloud_cover": 43}, {"timestamp": "2026-06-11T21:45:11.055945+00:00", "station_id": "GDN_01", "temperature": 14.25, "humidity": 54.07, "pressure": 1027.09, "wind_speed": 4.52, "wind_direction": 308, "rain_mm": 0, "cloud_cover": 96}, {"timestamp": "2026-06-11T21:35:11.055945+00:00", "station_id": "GDN_01", "temperature": 15.14, "humidity": 58.51, "pressure": 1010.79, "wind_speed": 10.66, "wind_direction": 56, "rain_mm": 0, "cloud_cover": 47}, {"timestamp": "2026-06-11T21:25:11.055945+00:00", "station_id": "GDN_01", "temperature": 19.22, "humidity": 90.6, "pressure": 1014.45, "wind_speed": 4.68, "wind_direction": 224, "rain_mm": 0, "cloud_cover": 74}, {"timestamp": "2026-06-11T21:15:11.055945+00:00", "station_id": "GDN_01", "temperature": 18.45, "humidity": 70.59, "pressure": 1022.44, "wind_speed": 9.96, "wind_direction": 205, "rain_mm": 0.25, "cloud_cover": 63}, {"timestamp": "2026-06-11T21:05:11.055945+00:00", "station_id": "GDN_01", "temperature": 15.52, "humidity": 64.06, "pressure": 1016.13, "wind_speed": 6.9, "wind_direction": 280, "rain_mm": 0, "cloud_cover": 87}, {"timestamp": "2026-06-11T20:55:11.055945+00:00", "station_id": "GDN_01", "temperature": 20.84, "humidity": 59.63, "pressure": 1005.23, "wind_speed": 8.19, "wind_direction": 218, "rain_mm": 1.3, "cloud_cover": 83}, {"timestamp": "2026-06-11T20:45:11.055945+00:00", "station_id": "GDN_01", "temperature": 20.54, "humidity": 48.97, "pressure": 1019.35, "wind_speed": 7.91, "wind_direction": 106, "rain_mm": 1.96, "cloud_cover": 2}, {"timestamp": "2026-06-11T20:35:11.055945+00:00", "station_id": "GDN_01", "temperature": 19.44, "humidity": 53.25, "pressure": 996.92, "wind_speed": 5.12, "wind_direction": 211, "rain_mm": 1.4, "cloud_cover": 17}, {"timestamp": "2026-06-11T20:25:11.055945+00:00", "station_id": "GDN_01", "temperature": 18.67, "humidity": 58.73, "pressure": 1004.77, "wind_speed": 2.95, "wind_direction": 163, "rain_mm": 0.17, "cloud_cover": 37}, {"timestamp": "2026-06-11T20:15:11.055945+00:00", "station_id": "GDN_01", "temperature": 14.68, "humidity": 77.99, "pressure": 1011.16, "wind_speed": 3.44, "wind_direction": 336, "rain_mm": 1.5, "cloud_cover": 34}, {"timestamp": "2026-06-11T20:05:11.055945+00:00", "station_id": "GDN_01", "temperature": 17.3, "humidity": 67.42, "pressure": 1011.82, "wind_speed": 3.67, "wind_direction": 105, "rain_mm": 1.21, "cloud_cover": 41}, {"timestamp": "2026-06-11T19:55:11.055945+00:00", "station_id": "GDN_01", "temperature": 18.41, "humidity": 69.26, "pressure": 1025.44, "wind_speed": 7.91, "wind_direction": 216, "rain_mm": 0, "cloud_cover": 38}, {"timestamp": "2026-06-11T19:45:11.055945+00:00", "station_id": "GDN_01", "temperature": 17.29, "humidity": 71.94, "pressure": 1028.04, "wind_speed": 9.54, "wind_direction": 7, "rain_mm": 1.45, "cloud_cover": 75}, {"timestamp": "2026-06-11T19:35:11.055945+00:00", "station_id": "GDN_01", "temperature": 17.29, "humidity": 77.95, "pressure": 1024.67, "wind_speed": 1.38, "wind_direction": 324, "rain_mm": 0, "cloud_cover": 13}, {"timestamp": "2026-06-11T19:25:11.055945+00:00", "station_id": "GDN_01", "temperature": 16.82, "humidity": 69.06, "pressure": 1009.65, "wind_speed": 13.85, "wind_direction": 199, "rain_mm": 1.59, "cloud_cover": 31}, {"timestamp": "2026-06-11T19:15:11.055945+00:00", "station_id": "GDN_01", "temperature": 14.91, "humidity": 93.39, "pressure": 1002.8, "wind_speed": 7.36, "wind_direction": 84, "rain_mm": 0.59, "cloud_cover": 6}, {"timestamp": "2026-06-11T19:05:11.055945+00:00", "station_id": "GDN_01", "temperature": 15.91, "humidity": 85.47, "pressure": 996.56, "wind_speed": 12.35, "wind_direction": 149, "rain_mm": 0, "cloud_cover": 24}, {"timestamp": "2026-06-11T18:55:11.055945+00:00", "station_id": "GDN_01", "temperature": 19.61, "humidity": 52.24, "pressure": 1001.43, "wind_speed": 7.58, "wind_direction": 38, "rain_mm": 1.7, "cloud_cover": 34}, {"timestamp": "2026-06-11T18:45:11.055945+00:00", "station_id": "GDN_01", "temperature": 20.85, "humidity": 67.92, "pressure": 1024.52, "wind_speed": 8.7, "wind_direction": 153, "rain_mm": 1.69, "cloud_cover": 22}, {"timestamp": "2026-06-11T18:35:11.055945+00:00", "station_id": "GDN_01", "temperature": 19.96, "humidity": 47.9, "pressure": 1026.16, "wind_speed": 12.55, "wind_direction": 42, "rain_mm": 0, "cloud_cover": 12}, {"timestamp": "2026-06-11T18:25:11.055945+00:00", "station_id": "GDN_01", "temperature": 17.67, "humidity": 59.07, "pressure": 1004.02, "wind_speed": 2.36, "wind_direction": 25, "rain_mm": 0.95, "cloud_cover": 96}, {"timestamp": "2026-06-11T18:15:11.055945+00:00", "station_id": "GDN_01", "temperature": 19.02, "humidity": 54.67, "pressure": 996.1, "wind_speed": 4.49, "wind_direction": 212, "rain_mm": 0.76, "cloud_cover": 84}, {"timestamp": "2026-06-11T18:05:11.055945+00:00", "station_id": "GDN_01", "temperature": 18.06, "humidity": 46.57, "pressure": 1026.42, "wind_speed": 12.95, "wind_direction": 176, "rain_mm": 0.49, "cloud_cover": 19}, {"timestamp": "2026-06-11T17:55:11.055945+00:00", "station_id": "GDN_01", "temperature": 19.12, "humidity": 65.05, "pressure": 1017.35, "wind_speed": 13.25, "wind_direction": 166, "rain_mm": 1.74, "cloud_cover": 4}, {"timestamp": "2026-06-11T17:45:11.055945+00:00", "station_id": "GDN_01", "temperature": 20.94, "humidity": 83.38, "pressure": 1027.29, "wind_speed": 11.66, "wind_direction": 194, "rain_mm": 0.7, "cloud_cover": 91}, {"timestamp": "2026-06-11T17:35:11.055945+00:00", "station_id": "GDN_01", "temperature": 17.55, "humidity": 77.38, "pressure": 1020.97, "wind_speed": 4.04, "wind_direction": 129, "rain_mm": 1.42, "cloud_cover": 25}, {"timestamp": "2026-06-11T17:25:11.055945+00:00", "station_id": "GDN_01", "temperature": 15.44, "humidity": 89.01, "pressure": 995.25, "wind_speed": 2.27, "wind_direction": 304, "rain_mm": 0.47, "cloud_cover": 90}, {"timestamp": "2026-06-11T17:15:11.055945+00:00", "station_id": "GDN_01", "temperature": 13.27, "humidity": 85.54, "pressure": 995.29, "wind_speed": 7.23, "wind_direction": 205, "rain_mm": 0.08, "cloud_cover": 11}, {"timestamp": "2026-06-11T17:05:11.055945+00:00", "station_id": "GDN_01", "temperature": 18.06, "humidity": 84.79, "pressure": 1018.88, "wind_speed": 13.9, "wind_direction": 349, "rain_mm": 0.33, "cloud_cover": 17}, {"timestamp": "2026-06-11T16:55:11.055945+00:00", "station_id": "GDN_01", "temperature": 18.28, "humidity": 55.88, "pressure": 1006.69, "wind_speed": 2.15, "wind_direction": 115, "rain_mm": 0, "cloud_cover": 4}, {"timestamp": "2026-06-11T16:45:11.055945+00:00", "station_id": "GDN_01", "temperature": 13.19, "humidity": 51.38, "pressure": 1023.92, "wind_speed": 10.6, "wind_direction": 10, "rain_mm": 1.27, "cloud_cover": 71}, {"timestamp": "2026-06-11T16:35:11.055945+00:00", "station_id": "GDN_01", "temperature": 19.71, "humidity": 51.45, "pressure": 1027.04, "wind_speed": 10.73, "wind_direction": 51, "rain_mm": 1.55, "cloud_cover": 29}, {"timestamp": "2026-06-11T16:25:11.055945+00:00", "station_id": "GDN_01", "temperature": 13.3, "humidity": 93.59, "pressure": 1016.81, "wind_speed": 4.64, "wind_direction": 66, "rain_mm": 1.04, "cloud_cover": 11}, {"timestamp": "2026-06-11T16:15:11.055945+00:00", "station_id": "GDN_01", "temperature": 14.89, "humidity": 60.75, "pressure": 1024.11, "wind_speed": 7.33, "wind_direction": 37, "rain_mm": 0, "cloud_cover": 93}, {"timestamp": "2026-06-11T16:05:11.055945+00:00", "station_id": "GDN_01", "temperature": 18.0, "humidity": 75.76, "pressure": 1024.51, "wind_speed": 4.37, "wind_direction": 178, "rain_mm": 0, "cloud_cover": 17}, {"timestamp": "2026-06-11T15:55:11.055945+00:00", "station_id": "GDN_01", "temperature": 19.38, "humidity": 94.54, "pressure": 1004.81, "wind_speed": 8.23, "wind_direction": 286, "rain_mm": 0, "cloud_cover": 5}, {"timestamp": "2026-06-11T15:45:11.055945+00:00", "station_id": "GDN_01", "temperature": 15.46, "humidity": 54.11, "pressure": 999.63, "wind_speed": 10.05, "wind_direction": 94, "rain_mm": 0.17, "cloud_cover": 0}, {"timestamp": "2026-06-11T15:35:11.055945+00:00", "station_id": "GDN_01", "temperature": 17.51, "humidity": 48.97, "pressure": 998.34, "wind_speed": 0.86, "wind_direction": 237, "rain_mm": 1.27, "cloud_cover": 91}, {"timestamp": "2026-06-11T15:25:11.055945+00:00", "station_id": "GDN_01", "temperature": 13.58, "humidity": 60.87, "pressure": 1017.79, "wind_speed": 7.28, "wind_direction": 255, "rain_mm": 0, "cloud_cover": 82}, {"timestamp": "2026-06-11T15:15:11.055945+00:00", "station_id": "GDN_01", "temperature": 14.14, "humidity": 60.03, "pressure": 1025.65, "wind_speed": 4.98, "wind_direction": 168, "rain_mm": 0, "cloud_cover": 4}, {"timestamp": "2026-06-11T15:05:11.055945+00:00", "station_id": "GDN_01", "temperature": 14.63, "humidity": 77.82, "pressure": 1008.4, "wind_speed": 12.98, "wind_direction": 121, "rain_mm": 0.58, "cloud_cover": 41}, {"timestamp": "2026-06-11T14:55:11.055945+00:00", "station_id": "GDN_01", "temperature": 13.41, "humidity": 72.89, "pressure": 1015.53, "wind_speed": 13.03, "wind_direction": 149, "rain_mm": 0, "cloud_cover": 40}, {"timestamp": "2026-06-11T14:45:11.055945+00:00", "station_id": "GDN_01", "temperature": 15.56, "humidity": 86.28, "pressure": 1028.79, "wind_speed": 9.91, "wind_direction": 28, "rain_mm": 1.51, "cloud_cover": 90}, {"timestamp": "2026-06-11T14:35:11.055945+00:00", "station_id": "GDN_01", "temperature": 14.25, "humidity": 55.27, "pressure": 1000.3, "wind_speed": 10.22, "wind_direction": 296, "rain_mm": 0, "cloud_cover": 42}, {"timestamp": "2026-06-11T14:25:11.055945+00:00", "station_id": "GDN_01", "temperature": 15.32, "humidity": 79.0, "pressure": 997.37, "wind_speed": 11.48, "wind_direction": 4, "rain_mm": 0, "cloud_cover": 23}, {"timestamp": "2026-06-11T14:15:11.055945+00:00", "station_id": "GDN_01", "temperature": 19.2, "humidity": 51.28, "pressure": 1015.13, "wind_speed": 11.46, "wind_direction": 159, "rain_mm": 0.03, "cloud_cover": 22}, {"timestamp": "2026-06-11T14:05:11.055945+00:00", "station_id": "GDN_01", "temperature": 20.03, "humidity": 68.93, "pressure": 1028.64, "wind_speed": 9.35, "wind_direction": 343, "rain_mm": 0, "cloud_cover": 50}, {"timestamp": "2026-06-11T13:55:11.055945+00:00", "station_id": "GDN_01", "temperature": 20.16, "humidity": 75.21, "pressure": 1022.43, "wind_speed": 1.59, "wind_direction": 269, "rain_mm": 0.72, "cloud_cover": 59}, {"timestamp": "2026-06-11T13:45:11.055945+00:00", "station_id": "GDN_01", "temperature": 18.0, "humidity": 78.26, "pressure": 1019.71, "wind_speed": 1.55, "wind_direction": 358, "rain_mm": 0.03, "cloud_cover": 25}, {"timestamp": "2026-06-11T13:35:11.055945+00:00", "station_id": "GDN_01", "temperature": 20.16, "humidity": 94.56, "pressure": 1004.81, "wind_speed": 12.94, "wind_direction": 85, "rain_mm": 0.83, "cloud_cover": 85}, {"timestamp": "2026-06-11T13:25:11.055945+00:00", "station_id": "GDN_01", "temperature": 14.75, "humidity": 51.44, "pressure": 1023.02, "wind_speed": 4.4, "wind_direction": 323, "rain_mm": 0, "cloud_cover": 87}, {"timestamp": "2026-06-11T13:15:11.055945+00:00", "station_id": "GDN_01", "temperature": 16.01, "humidity": 52.91, "pressure": 1027.8, "wind_speed": 12.77, "wind_direction": 133, "rain_mm": 1.66, "cloud_cover": 73}, {"timestamp": "2026-06-11T13:05:11.055945+00:00", "station_id": "GDN_01", "temperature": 17.17, "humidity": 51.3, "pressure": 1004.38, "wind_speed": 12.4, "wind_direction": 124, "rain_mm": 0.29, "cloud_cover": 28}, {"timestamp": "2026-06-11T12:55:11.055945+00:00", "station_id": "GDN_01", "temperature": 15.6, "humidity": 88.5, "pressure": 1013.14, "wind_speed": 5.45, "wind_direction": 2, "rain_mm": 0.68, "cloud_cover": 79}, {"timestamp": "2026-06-11T12:45:11.055945+00:00", "station_id": "GDN_01", "temperature": 20.34, "humidity": 54.07, "pressure": 1025.69, "wind_speed": 13.65, "wind_direction": 202, "rain_mm": 0.51, "cloud_cover": 19}, {"timestamp": "2026-06-11T12:35:11.055945+00:00", "station_id": "GDN_01", "temperature": 15.47, "humidity": 56.19, "pressure": 1000.83, "wind_speed": 10.59, "wind_direction": 341, "rain_mm": 0.54, "cloud_cover": 14}, {"timestamp": "2026-06-11T12:25:11.055945+00:00", "station_id": "GDN_01", "temperature": 16.67, "humidity": 63.97, "pressure": 1018.73, "wind_speed": 11.89, "wind_direction": 274, "rain_mm": 0.5, "cloud_cover": 27}, {"timestamp": "2026-06-11T12:15:11.055945+00:00", "station_id": "GDN_01", "temperature": 17.13, "humidity": 83.22, "pressure": 1009.51, "wind_speed": 3.4, "wind_direction": 32, "rain_mm": 0, "cloud_cover": 64}, {"timestamp": "2026-06-11T12:05:11.055945+00:00", "station_id": "GDN_01", "temperature": 14.63, "humidity": 88.69, "pressure": 1025.44, "wind_speed": 12.72, "wind_direction": 213, "rain_mm": 0.11, "cloud_cover": 3}, {"timestamp": "2026-06-11T11:55:11.055945+00:00", "station_id": "GDN_01", "temperature": 14.58, "humidity": 52.19, "pressure": 1022.57, "wind_speed": 1.99, "wind_direction": 49, "rain_mm": 1.08, "cloud_cover": 34}, {"timestamp": "2026-06-11T11:45:11.055945+00:00", "station_id": "GDN_01", "temperature": 19.03, "humidity": 62.39, "pressure": 1010.01, "wind_speed": 2.51, "wind_direction": 234, "rain_mm": 1.4, "cloud_cover": 8}, {"timestamp": "2026-06-11T11:35:11.055945+00:00", "station_id": "GDN_01", "temperature": 14.91, "humidity": 76.12, "pressure": 1010.73, "wind_speed": 9.2, "wind_direction": 167, "rain_mm": 0, "cloud_cover": 80}, {"timestamp": "2026-06-11T11:25:11.055945+00:00", "station_id": "GDN_01", "temperature": 16.9, "humidity": 67.52, "pressure": 1018.4, "wind_speed": 10.84, "wind_direction": 69, "rain_mm": 0, "cloud_cover": 82}, {"timestamp": "2026-06-11T11:15:11.055945+00:00", "station_id": "GDN_01", "temperature": 20.89, "humidity": 69.11, "pressure": 995.18, "wind_speed": 1.85, "wind_direction": 265, "rain_mm": 0.71, "cloud_cover": 17}, {"timestamp": "2026-06-11T11:05:11.055945+00:00", "station_id": "GDN_01", "temperature": 17.12, "humidity": 71.86, "pressure": 1015.43, "wind_speed": 7.32, "wind_direction": 30, "rain_mm": 0, "cloud_cover": 2}, {"timestamp": "2026-06-11T10:55:11.055945+00:00", "station_id": "GDN_01", "temperature": 16.89, "humidity": 60.35, "pressure": 1007.2, "wind_speed": 6.48, "wind_direction": 286, "rain_mm": 1.54, "cloud_cover": 94}, {"timestamp": "2026-06-11T10:45:11.055945+00:00", "station_id": "GDN_01", "temperature": 14.17, "humidity": 81.67, "pressure": 1001.6, "wind_speed": 4.94, "wind_direction": 58, "rain_mm": 1.6, "cloud_cover": 74}, {"timestamp": "2026-06-11T10:35:11.055945+00:00", "station_id": "GDN_01", "temperature": 18.06, "humidity": 57.52, "pressure": 1013.23, "wind_speed": 10.4, "wind_direction": 282, "rain_mm": 0.65, "cloud_cover": 73}, {"timestamp": "2026-06-11T10:25:11.055945+00:00", "station_id": "GDN_01", "temperature": 18.78, "humidity": 52.77, "pressure": 1029.34, "wind_speed": 6.87, "wind_direction": 9, "rain_mm": 0, "cloud_cover": 71}, {"timestamp": "2026-06-11T10:15:11.055945+00:00", "station_id": "GDN_01", "temperature": 14.38, "humidity": 66.67, "pressure": 995.72, "wind_speed": 1.26, "wind_direction": 79, "rain_mm": 0.22, "cloud_cover": 94}, {"timestamp": "2026-06-11T10:05:11.055945+00:00", "station_id": "GDN_01", "temperature": 20.74, "humidity": 68.54, "pressure": 1003.8, "wind_speed": 2.97, "wind_direction": 220, "rain_mm": 0.34, "cloud_cover": 42}, {"timestamp": "2026-06-11T09:55:11.055945+00:00", "station_id": "GDN_01", "temperature": 15.75, "humidity": 81.74, "pressure": 1002.99, "wind_speed": 10.62, "wind_direction": 246, "rain_mm": 0.65, "cloud_cover": 56}, {"timestamp": "2026-06-11T09:45:11.055945+00:00", "station_id": "GDN_01", "temperature": 18.6, "humidity": 50.71, "pressure": 995.11, "wind_speed": 12.7, "wind_direction": 337, "rain_mm": 0.18, "cloud_cover": 13}, {"timestamp": "2026-06-11T09:35:11.055945+00:00", "station_id": "GDN_01", "temperature": 20.57, "humidity": 65.22, "pressure": 1028.2, "wind_speed": 9.37, "wind_direction": 173, "rain_mm": 1.61, "cloud_cover": 77}, {"timestamp": "2026-06-11T09:25:11.055945+00:00", "station_id": "GDN_01", "temperature": 16.37, "humidity": 75.68, "pressure": 1018.74, "wind_speed": 0.8, "wind_direction": 179, "rain_mm": 0, "cloud_cover": 93}, {"timestamp": "2026-06-11T09:15:11.055945+00:00", "station_id": "GDN_01", "temperature": 19.36, "humidity": 86.51, "pressure": 1020.79, "wind_speed": 6.85, "wind_direction": 200, "rain_mm": 0, "cloud_cover": 97}, {"timestamp": "2026-06-11T09:05:11.055945+00:00", "station_id": "GDN_01", "temperature": 13.96, "humidity": 85.92, "pressure": 1017.27, "wind_speed": 10.48, "wind_direction": 250, "rain_mm": 0.2, "cloud_cover": 53}, {"timestamp": "2026-06-11T08:55:11.055945+00:00", "station_id": "GDN_01", "temperature": 20.42, "humidity": 52.04, "pressure": 1015.35, "wind_speed": 11.78, "wind_direction": 313, "rain_mm": 0.48, "cloud_cover": 64}, {"timestamp": "2026-06-11T08:45:11.055945+00:00", "station_id": "GDN_01", "temperature": 17.45, "humidity": 54.09, "pressure": 1001.43, "wind_speed": 5.15, "wind_direction": 167, "rain_mm": 0.04, "cloud_cover": 45}, {"timestamp": "2026-06-11T08:35:11.055945+00:00", "station_id": "GDN_01", "temperature": 19.48, "humidity": 81.38, "pressure": 1022.82, "wind_speed": 0.97, "wind_direction": 202, "rain_mm": 0, "cloud_cover": 79}, {"timestamp": "2026-06-11T08:25:11.055945+00:00", "station_id": "GDN_01", "temperature": 20.43, "humidity": 52.07, "pressure": 1010.76, "wind_speed": 11.55, "wind_direction": 352, "rain_mm": 0, "cloud_cover": 22}, {"timestamp": "2026-06-11T08:15:11.055945+00:00", "station_id": "GDN_01", "temperature": 20.92, "humidity": 70.14, "pressure": 1009.33, "wind_speed": 9.73, "wind_direction": 131, "rain_mm": 1.17, "cloud_cover": 68}, {"timestamp": "2026-06-11T08:05:11.055945+00:00", "station_id": "GDN_01", "temperature": 18.02, "humidity": 87.1, "pressure": 1016.28, "wind_speed": 5.9, "wind_direction": 53, "rain_mm": 0, "cloud_cover": 37}, {"timestamp": "2026-06-11T07:55:11.055945+00:00", "station_id": "GDN_01", "temperature": 20.62, "humidity": 50.85, "pressure": 996.82, "wind_speed": 11.3, "wind_direction": 320, "rain_mm": 0.45, "cloud_cover": 21}, {"timestamp": "2026-06-11T07:45:11.055945+00:00", "station_id": "GDN_01", "temperature": 20.77, "humidity": 75.47, "pressure": 1006.89, "wind_speed": 3.08, "wind_direction": 146, "rain_mm": 1.1, "cloud_cover": 94}, {"timestamp": "2026-06-11T07:35:11.055945+00:00", "station_id": "GDN_01", "temperature": 20.4, "humidity": 86.07, "pressure": 1015.53, "wind_speed": 11.37, "wind_direction": 316, "rain_mm": 0.53, "cloud_cover": 11}, {"timestamp": "2026-06-11T07:25:11.055945+00:00", "station_id": "GDN_01", "temperature": 13.36, "humidity": 74.14, "pressure": 1002.78, "wind_speed": 12.0, "wind_direction": 213, "rain_mm": 1.2, "cloud_cover": 67}, {"timestamp": "2026-06-11T07:15:11.055945+00:00", "station_id": "GDN_01", "temperature": 14.92, "humidity": 69.52, "pressure": 1016.27, "wind_speed": 9.26, "wind_direction": 259, "rain_mm": 1.97, "cloud_cover": 63}, {"timestamp": "2026-06-11T07:05:11.055945+00:00", "station_id": "GDN_01", "temperature": 13.97, "humidity": 80.29, "pressure": 997.75, "wind_speed": 10.31, "wind_direction": 18, "rain_mm": 2.01, "cloud_cover": 19}, {"timestamp": "2026-06-11T06:55:11.055945+00:00", "station_id": "GDN_01", "temperature": 13.27, "humidity": 46.94, "pressure": 1018.5, "wind_speed": 8.03, "wind_direction": 71, "rain_mm": 1.78, "cloud_cover": 21}, {"timestamp": "2026-06-11T06:45:11.055945+00:00", "station_id": "GDN_01", "temperature": 15.6, "humidity": 55.78, "pressure": 997.78, "wind_speed": 3.58, "wind_direction": 258, "rain_mm": 1.43, "cloud_cover": 17}, {"timestamp": "2026-06-11T06:35:11.055945+00:00", "station_id": "GDN_01", "temperature": 18.39, "humidity": 48.98, "pressure": 1027.5, "wind_speed": 9.93, "wind_direction": 230, "rain_mm": 2.81, "cloud_cover": 7}, {"timestamp": "2026-06-11T06:25:11.055945+00:00", "station_id": "GDN_01", "temperature": 13.14, "humidity": 65.88, "pressure": 1012.09, "wind_speed": 6.25, "wind_direction": 61, "rain_mm": 0.08, "cloud_cover": 80}, {"timestamp": "2026-06-11T06:15:11.055945+00:00", "station_id": "GDN_01", "temperature": 17.51, "humidity": 89.07, "pressure": 1002.44, "wind_speed": 10.84, "wind_direction": 115, "rain_mm": 0.25, "cloud_cover": 79}, {"timestamp": "2026-06-11T06:05:11.055945+00:00", "station_id": "GDN_01", "temperature": 19.14, "humidity": 64.26, "pressure": 1009.69, "wind_speed": 8.03, "wind_direction": 299, "rain_mm": 0, "cloud_cover": 94}, {"timestamp": "2026-06-11T05:55:11.055945+00:00", "station_id": "GDN_01", "temperature": 20.78, "humidity": 91.43, "pressure": 1012.57, "wind_speed": 12.67, "wind_direction": 32, "rain_mm": 0, "cloud_cover": 30}, {"timestamp": "2026-06-11T05:45:11.055945+00:00", "station_id": "GDN_01", "temperature": 16.78, "humidity": 86.62, "pressure": 1002.62, "wind_speed": 5.65, "wind_direction": 357, "rain_mm": 1.34, "cloud_cover": 86}, {"timestamp": "2026-06-11T05:35:11.055945+00:00", "station_id": "GDN_01", "temperature": 13.42, "humidity": 86.08, "pressure": 1000.27, "wind_speed": 12.52, "wind_direction": 167, "rain_mm": 1.12, "cloud_cover": 26}, {"timestamp": "2026-06-11T05:25:11.055945+00:00", "station_id": "GDN_01", "temperature": 19.17, "humidity": 55.56, "pressure": 997.78, "wind_speed": 1.83, "wind_direction": 82, "rain_mm": 1.37, "cloud_cover": 70}, {"timestamp": "2026-06-11T05:15:11.055945+00:00", "station_id": "GDN_01", "temperature": 19.37, "humidity": 80.6, "pressure": 1009.73, "wind_speed": 6.86, "wind_direction": 354, "rain_mm": 2.8, "cloud_cover": 51}, {"timestamp": "2026-06-11T05:05:11.055945+00:00", "station_id": "GDN_01", "temperature": 17.86, "humidity": 48.99, "pressure": 1025.68, "wind_speed": 11.72, "wind_direction": 48, "rain_mm": 0, "cloud_cover": 43}, {"timestamp": "2026-06-11T04:55:11.055945+00:00", "station_id": "GDN_01", "temperature": 17.93, "humidity": 53.26, "pressure": 1025.62, "wind_speed": 9.32, "wind_direction": 49, "rain_mm": 0.22, "cloud_cover": 70}, {"timestamp": "2026-06-11T04:45:11.055945+00:00", "station_id": "GDN_01", "temperature": 21.0, "humidity": 61.91, "pressure": 999.32, "wind_speed": 2.65, "wind_direction": 324, "rain_mm": 0.0, "cloud_cover": 89}, {"timestamp": "2026-06-11T04:35:11.055945+00:00", "station_id": "GDN_01", "temperature": 16.4, "humidity": 49.8, "pressure": 1018.24, "wind_speed": 7.44, "wind_direction": 223, "rain_mm": 0, "cloud_cover": 51}, {"timestamp": "2026-06-11T04:25:11.055945+00:00", "station_id": "GDN_01", "temperature": 13.92, "humidity": 46.45, "pressure": 1020.74, "wind_speed": 7.95, "wind_direction": 149, "rain_mm": 0, "cloud_cover": 5}, {"timestamp": "2026-06-11T04:15:11.055945+00:00", "station_id": "GDN_01", "temperature": 19.77, "humidity": 61.8, "pressure": 995.29, "wind_speed": 7.72, "wind_direction": 327, "rain_mm": 0.39, "cloud_cover": 9}]}