{"station_id": "GDN_01", "count": 200, "records": [{"timestamp": "2026-06-12T13:54:28.945850+00:00", "station_id": "GDN_01", "temperature": 19.47, "humidity": 57.47, "pressure": 1004.17, "wind_speed": 1.25, "wind_direction": 101, "rain_mm": 0.66, "cloud_cover": 83}, {"timestamp": "2026-06-12T13:44:28.945850+00:00", "station_id": "GDN_01", "temperature": 17.65, "humidity": 79.97, "pressure": 1011.39, "wind_speed": 6.05, "wind_direction": 163, "rain_mm": 1.82, "cloud_cover": 47}, {"timestamp": "2026-06-12T13:34:28.945850+00:00", "station_id": "GDN_01", "temperature": 18.88, "humidity": 79.46, "pressure": 1024.47, "wind_speed": 7.84, "wind_direction": 149, "rain_mm": 1.38, "cloud_cover": 100}, {"timestamp": "2026-06-12T13:24:28.945850+00:00", "station_id": "GDN_01", "temperature": 16.25, "humidity": 61.37, "pressure": 1003.56, "wind_speed": 12.39, "wind_direction": 309, "rain_mm": 0.32, "cloud_cover": 36}, {"timestamp": "2026-06-12T13:14:28.945850+00:00", "station_id": "GDN_01", "temperature": 15.96, "humidity": 53.85, "pressure": 1001.0, "wind_speed": 4.86, "wind_direction": 233, "rain_mm": 0, "cloud_cover": 31}, {"timestamp": "2026-06-12T13:04:28.945850+00:00", "station_id": "GDN_01", "temperature": 13.66, "humidity": 82.14, "pressure": 1010.97, "wind_speed": 13.3, "wind_direction": 124, "rain_mm": 0, "cloud_cover": 24}, {"timestamp": "2026-06-12T12:54:28.945850+00:00", "station_id": "GDN_01", "temperature": 15.52, "humidity": 77.53, "pressure": 995.74, "wind_speed": 6.87, "wind_direction": 260, "rain_mm": 1.17, "cloud_cover": 40}, {"timestamp": "2026-06-12T12:44:28.945850+00:00", "station_id": "GDN_01", "temperature": 13.06, "humidity": 63.45, "pressure": 999.51, "wind_speed": 7.96, "wind_direction": 2, "rain_mm": 0, "cloud_cover": 25}, {"timestamp": "2026-06-12T12:34:28.945850+00:00", "station_id": "GDN_01", "temperature": 14.94, "humidity": 93.04, "pressure": 1025.76, "wind_speed": 10.0, "wind_direction": 277, "rain_mm": 0.39, "cloud_cover": 90}, {"timestamp": "2026-06-12T12:24:28.945850+00:00", "station_id": "GDN_01", "temperature": 13.96, "humidity": 67.59, "pressure": 1000.13, "wind_speed": 9.63, "wind_direction": 51, "rain_mm": 0, "cloud_cover": 71}, {"timestamp": "2026-06-12T12:14:28.945850+00:00", "station_id": "GDN_01", "temperature": 19.04, "humidity": 73.89, "pressure": 1000.06, "wind_speed": 2.17, "wind_direction": 210, "rain_mm": 0.46, "cloud_cover": 69}, {"timestamp": "2026-06-12T12:04:28.945850+00:00", "station_id": "GDN_01", "temperature": 17.18, "humidity": 56.01, "pressure": 1018.47, "wind_speed": 8.9, "wind_direction": 260, "rain_mm": 0.87, "cloud_cover": 68}, {"timestamp": "2026-06-12T11:54:28.945850+00:00", "station_id": "GDN_01", "temperature": 17.02, "humidity": 87.08, "pressure": 995.09, "wind_speed": 7.89, "wind_direction": 78, "rain_mm": 0.39, "cloud_cover": 37}, {"timestamp": "2026-06-12T11:44:28.945850+00:00", "station_id": "GDN_01", "temperature": 15.6, "humidity": 54.08, "pressure": 1009.82, "wind_speed": 11.84, "wind_direction": 277, "rain_mm": 0, "cloud_cover": 61}, {"timestamp": "2026-06-12T11:34:28.945850+00:00", "station_id": "GDN_01", "temperature": 18.95, "humidity": 73.76, "pressure": 1016.88, "wind_speed": 9.76, "wind_direction": 33, "rain_mm": 0.53, "cloud_cover": 5}, {"timestamp": "2026-06-12T11:24:28.945850+00:00", "station_id": "GDN_01", "temperature": 17.94, "humidity": 80.85, "pressure": 1011.74, "wind_speed": 10.83, "wind_direction": 87, "rain_mm": 0, "cloud_cover": 9}, {"timestamp": "2026-06-12T11:14:28.945850+00:00", "station_id": "GDN_01", "temperature": 15.56, "humidity": 55.36, "pressure": 1000.73, "wind_speed": 9.24, "wind_direction": 201, "rain_mm": 0.18, "cloud_cover": 27}, {"timestamp": "2026-06-12T11:04:28.945850+00:00", "station_id": "GDN_01", "temperature": 16.86, "humidity": 79.09, "pressure": 1012.93, "wind_speed": 7.86, "wind_direction": 23, "rain_mm": 1.46, "cloud_cover": 87}, {"timestamp": "2026-06-12T10:54:28.945850+00:00", "station_id": "GDN_01", "temperature": 19.59, "humidity": 82.02, "pressure": 1022.43, "wind_speed": 6.15, "wind_direction": 242, "rain_mm": 0, "cloud_cover": 39}, {"timestamp": "2026-06-12T10:44:28.945850+00:00", "station_id": "GDN_01", "temperature": 20.81, "humidity": 66.34, "pressure": 1023.09, "wind_speed": 7.08, "wind_direction": 201, "rain_mm": 2.59, "cloud_cover": 73}, {"timestamp": "2026-06-12T10:34:28.945850+00:00", "station_id": "GDN_01", "temperature": 16.37, "humidity": 72.75, "pressure": 1016.68, "wind_speed": 5.35, "wind_direction": 152, "rain_mm": 1.08, "cloud_cover": 95}, {"timestamp": "2026-06-12T10:24:28.945850+00:00", "station_id": "GDN_01", "temperature": 18.29, "humidity": 78.83, "pressure": 1011.43, "wind_speed": 8.24, "wind_direction": 29, "rain_mm": 0.79, "cloud_cover": 52}, {"timestamp": "2026-06-12T10:14:28.945850+00:00", "station_id": "GDN_01", "temperature": 20.44, "humidity": 70.16, "pressure": 1020.96, "wind_speed": 8.33, "wind_direction": 37, "rain_mm": 0.85, "cloud_cover": 35}, {"timestamp": "2026-06-12T10:04:28.945850+00:00", "station_id": "GDN_01", "temperature": 15.43, "humidity": 89.68, "pressure": 1012.96, "wind_speed": 1.64, "wind_direction": 124, "rain_mm": 0, "cloud_cover": 45}, {"timestamp": "2026-06-12T09:54:28.945850+00:00", "station_id": "GDN_01", "temperature": 19.36, "humidity": 64.91, "pressure": 1027.3, "wind_speed": 13.8, "wind_direction": 337, "rain_mm": 1.45, "cloud_cover": 30}, {"timestamp": "2026-06-12T09:44:28.945850+00:00", "station_id": "GDN_01", "temperature": 14.91, "humidity": 52.6, "pressure": 1028.66, "wind_speed": 10.67, "wind_direction": 190, "rain_mm": 0, "cloud_cover": 11}, {"timestamp": "2026-06-12T09:34:28.945850+00:00", "station_id": "GDN_01", "temperature": 16.42, "humidity": 48.92, "pressure": 1028.88, "wind_speed": 10.1, "wind_direction": 347, "rain_mm": 0, "cloud_cover": 95}, {"timestamp": "2026-06-12T09:24:28.945850+00:00", "station_id": "GDN_01", "temperature": 18.38, "humidity": 67.99, "pressure": 1007.96, "wind_speed": 9.56, "wind_direction": 95, "rain_mm": 0, "cloud_cover": 52}, {"timestamp": "2026-06-12T09:14:28.945850+00:00", "station_id": "GDN_01", "temperature": 20.75, "humidity": 56.74, "pressure": 1014.06, "wind_speed": 6.73, "wind_direction": 51, "rain_mm": 0.57, "cloud_cover": 32}, {"timestamp": "2026-06-12T09:04:28.945850+00:00", "station_id": "GDN_01", "temperature": 17.03, "humidity": 48.69, "pressure": 1023.15, "wind_speed": 12.71, "wind_direction": 110, "rain_mm": 0, "cloud_cover": 13}, {"timestamp": "2026-06-12T08:54:28.945850+00:00", "station_id": "GDN_01", "temperature": 20.92, "humidity": 60.8, "pressure": 1006.1, "wind_speed": 1.54, "wind_direction": 131, "rain_mm": 0.57, "cloud_cover": 76}, {"timestamp": "2026-06-12T08:44:28.945850+00:00", "station_id": "GDN_01", "temperature": 20.68, "humidity": 66.38, "pressure": 1015.8, "wind_speed": 13.24, "wind_direction": 268, "rain_mm": 0.31, "cloud_cover": 65}, {"timestamp": "2026-06-12T08:34:28.945850+00:00", "station_id": "GDN_01", "temperature": 16.68, "humidity": 94.8, "pressure": 1026.95, "wind_speed": 3.75, "wind_direction": 144, "rain_mm": 0, "cloud_cover": 44}, {"timestamp": "2026-06-12T08:24:28.945850+00:00", "station_id": "GDN_01", "temperature": 13.9, "humidity": 81.98, "pressure": 999.86, "wind_speed": 8.51, "wind_direction": 47, "rain_mm": 0.27, "cloud_cover": 37}, {"timestamp": "2026-06-12T08:14:28.945850+00:00", "station_id": "GDN_01", "temperature": 19.97, "humidity": 62.11, "pressure": 1021.34, "wind_speed": 1.97, "wind_direction": 118, "rain_mm": 1.0, "cloud_cover": 66}, {"timestamp": "2026-06-12T08:04:28.945850+00:00", "station_id": "GDN_01", "temperature": 16.41, "humidity": 82.41, "pressure": 1014.29, "wind_speed": 9.28, "wind_direction": 309, "rain_mm": 0, "cloud_cover": 52}, {"timestamp": "2026-06-12T07:54:28.945850+00:00", "station_id": "GDN_01", "temperature": 17.73, "humidity": 57.85, "pressure": 1018.59, "wind_speed": 13.39, "wind_direction": 327, "rain_mm": 0, "cloud_cover": 21}, {"timestamp": "2026-06-12T07:44:28.945850+00:00", "station_id": "GDN_01", "temperature": 18.99, "humidity": 85.85, "pressure": 1021.13, "wind_speed": 0.56, "wind_direction": 186, "rain_mm": 1.39, "cloud_cover": 1}, {"timestamp": "2026-06-12T07:34:28.945850+00:00", "station_id": "GDN_01", "temperature": 18.68, "humidity": 81.65, "pressure": 997.35, "wind_speed": 10.18, "wind_direction": 359, "rain_mm": 0, "cloud_cover": 37}, {"timestamp": "2026-06-12T07:24:28.945850+00:00", "station_id": "GDN_01", "temperature": 13.07, "humidity": 86.62, "pressure": 1004.36, "wind_speed": 11.43, "wind_direction": 31, "rain_mm": 1.11, "cloud_cover": 32}, {"timestamp": "2026-06-12T07:14:28.945850+00:00", "station_id": "GDN_01", "temperature": 15.27, "humidity": 58.54, "pressure": 996.9, "wind_speed": 10.42, "wind_direction": 332, "rain_mm": 0.84, "cloud_cover": 71}, {"timestamp": "2026-06-12T07:04:28.945850+00:00", "station_id": "GDN_01", "temperature": 19.73, "humidity": 66.14, "pressure": 1020.0, "wind_speed": 9.06, "wind_direction": 61, "rain_mm": 0, "cloud_cover": 77}, {"timestamp": "2026-06-12T06:54:28.945850+00:00", "station_id": "GDN_01", "temperature": 17.22, "humidity": 82.17, "pressure": 1003.73, "wind_speed": 5.79, "wind_direction": 33, "rain_mm": 0.72, "cloud_cover": 67}, {"timestamp": "2026-06-12T06:44:28.945850+00:00", "station_id": "GDN_01", "temperature": 17.26, "humidity": 54.36, "pressure": 1007.23, "wind_speed": 10.25, "wind_direction": 64, "rain_mm": 0.05, "cloud_cover": 21}, {"timestamp": "2026-06-12T06:34:28.945850+00:00", "station_id": "GDN_01", "temperature": 18.9, "humidity": 71.75, "pressure": 1029.88, "wind_speed": 5.96, "wind_direction": 66, "rain_mm": 0.99, "cloud_cover": 79}, {"timestamp": "2026-06-12T06:24:28.945850+00:00", "station_id": "GDN_01", "temperature": 20.16, "humidity": 85.58, "pressure": 1018.03, "wind_speed": 13.46, "wind_direction": 292, "rain_mm": 0.06, "cloud_cover": 12}, {"timestamp": "2026-06-12T06:14:28.945850+00:00", "station_id": "GDN_01", "temperature": 14.31, "humidity": 90.07, "pressure": 1016.79, "wind_speed": 12.21, "wind_direction": 221, "rain_mm": 2.14, "cloud_cover": 94}, {"timestamp": "2026-06-12T06:04:28.945850+00:00", "station_id": "GDN_01", "temperature": 13.7, "humidity": 90.19, "pressure": 1005.42, "wind_speed": 1.25, "wind_direction": 251, "rain_mm": 0, "cloud_cover": 53}, {"timestamp": "2026-06-12T05:54:28.945850+00:00", "station_id": "GDN_01", "temperature": 14.56, "humidity": 89.04, "pressure": 1010.8, "wind_speed": 5.93, "wind_direction": 243, "rain_mm": 0, "cloud_cover": 46}, {"timestamp": "2026-06-12T05:44:28.945850+00:00", "station_id": "GDN_01", "temperature": 13.4, "humidity": 81.45, "pressure": 1007.51, "wind_speed": 13.03, "wind_direction": 188, "rain_mm": 0.27, "cloud_cover": 49}, {"timestamp": "2026-06-12T05:34:28.945850+00:00", "station_id": "GDN_01", "temperature": 18.38, "humidity": 58.37, "pressure": 1026.16, "wind_speed": 0.66, "wind_direction": 335, "rain_mm": 0, "cloud_cover": 71}, {"timestamp": "2026-06-12T05:24:28.945850+00:00", "station_id": "GDN_01", "temperature": 14.59, "humidity": 56.16, "pressure": 1016.58, "wind_speed": 8.93, "wind_direction": 170, "rain_mm": 1.45, "cloud_cover": 31}, {"timestamp": "2026-06-12T05:14:28.945850+00:00", "station_id": "GDN_01", "temperature": 17.95, "humidity": 62.17, "pressure": 1017.1, "wind_speed": 6.83, "wind_direction": 245, "rain_mm": 2.16, "cloud_cover": 30}, {"timestamp": "2026-06-12T05:04:28.945850+00:00", "station_id": "GDN_01", "temperature": 18.19, "humidity": 61.36, "pressure": 1014.12, "wind_speed": 0.54, "wind_direction": 172, "rain_mm": 0.34, "cloud_cover": 71}, {"timestamp": "2026-06-12T04:54:28.945850+00:00", "station_id": "GDN_01", "temperature": 14.58, "humidity": 73.57, "pressure": 1001.04, "wind_speed": 8.42, "wind_direction": 165, "rain_mm": 0.96, "cloud_cover": 83}, {"timestamp": "2026-06-12T04:44:28.945850+00:00", "station_id": "GDN_01", "temperature": 18.2, "humidity": 61.01, "pressure": 1027.27, "wind_speed": 8.29, "wind_direction": 179, "rain_mm": 1.02, "cloud_cover": 17}, {"timestamp": "2026-06-12T04:34:28.945850+00:00", "station_id": "GDN_01", "temperature": 13.45, "humidity": 78.45, "pressure": 1028.94, "wind_speed": 0.4, "wind_direction": 26, "rain_mm": 0.41, "cloud_cover": 43}, {"timestamp": "2026-06-12T04:24:28.945850+00:00", "station_id": "GDN_01", "temperature": 19.09, "humidity": 73.25, "pressure": 1023.8, "wind_speed": 5.0, "wind_direction": 164, "rain_mm": 0, "cloud_cover": 1}, {"timestamp": "2026-06-12T04:14:28.945850+00:00", "station_id": "GDN_01", "temperature": 19.91, "humidity": 46.47, "pressure": 1009.73, "wind_speed": 6.56, "wind_direction": 146, "rain_mm": 0.45, "cloud_cover": 63}, {"timestamp": "2026-06-12T04:04:28.945850+00:00", "station_id": "GDN_01", "temperature": 19.99, "humidity": 80.52, "pressure": 1028.14, "wind_speed": 0.56, "wind_direction": 46, "rain_mm": 0, "cloud_cover": 81}, {"timestamp": "2026-06-12T03:54:28.945850+00:00", "station_id": "GDN_01", "temperature": 17.57, "humidity": 83.74, "pressure": 1016.64, "wind_speed": 4.85, "wind_direction": 83, "rain_mm": 2.35, "cloud_cover": 13}, {"timestamp": "2026-06-12T03:44:28.945850+00:00", "station_id": "GDN_01", "temperature": 17.87, "humidity": 74.57, "pressure": 1013.41, "wind_speed": 3.34, "wind_direction": 1, "rain_mm": 0, "cloud_cover": 69}, {"timestamp": "2026-06-12T03:34:28.945850+00:00", "station_id": "GDN_01", "temperature": 20.71, "humidity": 57.1, "pressure": 999.64, "wind_speed": 2.51, "wind_direction": 258, "rain_mm": 0, "cloud_cover": 17}, {"timestamp": "2026-06-12T03:24:28.945850+00:00", "station_id": "GDN_01", "temperature": 18.95, "humidity": 47.41, "pressure": 999.25, "wind_speed": 0.75, "wind_direction": 224, "rain_mm": 0.41, "cloud_cover": 66}, {"timestamp": "2026-06-12T03:14:28.945850+00:00", "station_id": "GDN_01", "temperature": 20.04, "humidity": 90.1, "pressure": 1003.97, "wind_speed": 2.78, "wind_direction": 275, "rain_mm": 0.69, "cloud_cover": 97}, {"timestamp": "2026-06-12T03:04:28.945850+00:00", "station_id": "GDN_01", "temperature": 20.52, "humidity": 53.64, "pressure": 1013.97, "wind_speed": 0.96, "wind_direction": 294, "rain_mm": 0, "cloud_cover": 28}, {"timestamp": "2026-06-12T02:54:28.945850+00:00", "station_id": "GDN_01", "temperature": 17.87, "humidity": 81.39, "pressure": 1002.15, "wind_speed": 0.05, "wind_direction": 188, "rain_mm": 1.17, "cloud_cover": 77}, {"timestamp": "2026-06-12T02:44:28.945850+00:00", "station_id": "GDN_01", "temperature": 18.94, "humidity": 91.47, "pressure": 1007.69, "wind_speed": 12.24, "wind_direction": 244, "rain_mm": 0.47, "cloud_cover": 88}, {"timestamp": "2026-06-12T02:34:28.945850+00:00", "station_id": "GDN_01", "temperature": 17.8, "humidity": 71.76, "pressure": 1008.37, "wind_speed": 2.53, "wind_direction": 60, "rain_mm": 1.86, "cloud_cover": 100}, {"timestamp": "2026-06-12T02:24:28.945850+00:00", "station_id": "GDN_01", "temperature": 16.71, "humidity": 59.59, "pressure": 1020.73, "wind_speed": 10.8, "wind_direction": 305, "rain_mm": 0, "cloud_cover": 85}, {"timestamp": "2026-06-12T02:14:28.945850+00:00", "station_id": "GDN_01", "temperature": 15.18, "humidity": 47.38, "pressure": 1020.46, "wind_speed": 1.83, "wind_direction": 342, "rain_mm": 1.29, "cloud_cover": 65}, {"timestamp": "2026-06-12T02:04:28.945850+00:00", "station_id": "GDN_01", "temperature": 18.62, "humidity": 49.88, "pressure": 1003.54, "wind_speed": 3.38, "wind_direction": 42, "rain_mm": 0.28, "cloud_cover": 73}, {"timestamp": "2026-06-12T01:54:28.945850+00:00", "station_id": "GDN_01", "temperature": 15.03, "humidity": 48.68, "pressure": 1025.75, "wind_speed": 6.07, "wind_direction": 146, "rain_mm": 1.62, "cloud_cover": 75}, {"timestamp": "2026-06-12T01:44:28.945850+00:00", "station_id": "GDN_01", "temperature": 15.53, "humidity": 55.85, "pressure": 1012.81, "wind_speed": 5.05, "wind_direction": 170, "rain_mm": 0, "cloud_cover": 8}, {"timestamp": "2026-06-12T01:34:28.945850+00:00", "station_id": "GDN_01", "temperature": 16.52, "humidity": 83.66, "pressure": 1009.3, "wind_speed": 10.88, "wind_direction": 79, "rain_mm": 0.65, "cloud_cover": 61}, {"timestamp": "2026-06-12T01:24:28.945850+00:00", "station_id": "GDN_01", "temperature": 15.45, "humidity": 53.78, "pressure": 1014.15, "wind_speed": 7.18, "wind_direction": 346, "rain_mm": 0.74, "cloud_cover": 89}, {"timestamp": "2026-06-12T01:14:28.945850+00:00", "station_id": "GDN_01", "temperature": 16.02, "humidity": 83.01, "pressure": 1029.47, "wind_speed": 3.66, "wind_direction": 221, "rain_mm": 0.5, "cloud_cover": 37}, {"timestamp": "2026-06-12T01:04:28.945850+00:00", "station_id": "GDN_01", "temperature": 13.48, "humidity": 70.11, "pressure": 1014.57, "wind_speed": 7.32, "wind_direction": 205, "rain_mm": 0, "cloud_cover": 81}, {"timestamp": "2026-06-12T00:54:28.945850+00:00", "station_id": "GDN_01", "temperature": 16.32, "humidity": 92.6, "pressure": 1005.01, "wind_speed": 1.8, "wind_direction": 73, "rain_mm": 1.07, "cloud_cover": 78}, {"timestamp": "2026-06-12T00:44:28.945850+00:00", "station_id": "GDN_01", "temperature": 15.61, "humidity": 49.74, "pressure": 1027.14, "wind_speed": 8.24, "wind_direction": 71, "rain_mm": 1.2, "cloud_cover": 81}, {"timestamp": "2026-06-12T00:34:28.945850+00:00", "station_id": "GDN_01", "temperature": 18.04, "humidity": 56.29, "pressure": 996.36, "wind_speed": 12.03, "wind_direction": 103, "rain_mm": 0, "cloud_cover": 8}, {"timestamp": "2026-06-12T00:24:28.945850+00:00", "station_id": "GDN_01", "temperature": 17.13, "humidity": 86.04, "pressure": 1022.49, "wind_speed": 12.74, "wind_direction": 243, "rain_mm": 0, "cloud_cover": 12}, {"timestamp": "2026-06-12T00:14:28.945850+00:00", "station_id": "GDN_01", "temperature": 19.54, "humidity": 65.28, "pressure": 1020.68, "wind_speed": 8.52, "wind_direction": 152, "rain_mm": 0, "cloud_cover": 95}, {"timestamp": "2026-06-12T00:04:28.945850+00:00", "station_id": "GDN_01", "temperature": 20.69, "humidity": 74.6, "pressure": 1017.87, "wind_speed": 12.0, "wind_direction": 309, "rain_mm": 0, "cloud_cover": 36}, {"timestamp": "2026-06-11T23:54:28.945850+00:00", "station_id": "GDN_01", "temperature": 17.17, "humidity": 80.69, "pressure": 1000.59, "wind_speed": 9.08, "wind_direction": 177, "rain_mm": 0.01, "cloud_cover": 81}, {"timestamp": "2026-06-11T23:44:28.945850+00:00", "station_id": "GDN_01", "temperature": 14.06, "humidity": 73.61, "pressure": 1006.65, "wind_speed": 2.72, "wind_direction": 320, "rain_mm": 1.49, "cloud_cover": 55}, {"timestamp": "2026-06-11T23:34:28.945850+00:00", "station_id": "GDN_01", "temperature": 15.58, "humidity": 77.48, "pressure": 1012.89, "wind_speed": 6.44, "wind_direction": 358, "rain_mm": 0.89, "cloud_cover": 45}, {"timestamp": "2026-06-11T23:24:28.945850+00:00", "station_id": "GDN_01", "temperature": 17.95, "humidity": 91.99, "pressure": 1017.82, "wind_speed": 13.2, "wind_direction": 128, "rain_mm": 0, "cloud_cover": 67}, {"timestamp": "2026-06-11T23:14:28.945850+00:00", "station_id": "GDN_01", "temperature": 16.83, "humidity": 54.31, "pressure": 1012.85, "wind_speed": 10.59, "wind_direction": 12, "rain_mm": 2.57, "cloud_cover": 81}, {"timestamp": "2026-06-11T23:04:28.945850+00:00", "station_id": "GDN_01", "temperature": 14.84, "humidity": 58.14, "pressure": 1023.05, "wind_speed": 7.65, "wind_direction": 295, "rain_mm": 1.68, "cloud_cover": 75}, {"timestamp": "2026-06-11T22:54:28.945850+00:00", "station_id": "GDN_01", "temperature": 20.73, "humidity": 47.83, "pressure": 1006.06, "wind_speed": 12.81, "wind_direction": 132, "rain_mm": 1.14, "cloud_cover": 75}, {"timestamp": "2026-06-11T22:44:28.945850+00:00", "station_id": "GDN_01", "temperature": 13.86, "humidity": 62.84, "pressure": 1007.58, "wind_speed": 2.92, "wind_direction": 120, "rain_mm": 0, "cloud_cover": 76}, {"timestamp": "2026-06-11T22:34:28.945850+00:00", "station_id": "GDN_01", "temperature": 13.14, "humidity": 45.15, "pressure": 1006.63, "wind_speed": 11.62, "wind_direction": 350, "rain_mm": 0.76, "cloud_cover": 85}, {"timestamp": "2026-06-11T22:24:28.945850+00:00", "station_id": "GDN_01", "temperature": 15.07, "humidity": 53.34, "pressure": 1025.28, "wind_speed": 7.62, "wind_direction": 254, "rain_mm": 0, "cloud_cover": 2}, {"timestamp": "2026-06-11T22:14:28.945850+00:00", "station_id": "GDN_01", "temperature": 18.18, "humidity": 61.54, "pressure": 1012.46, "wind_speed": 11.62, "wind_direction": 153, "rain_mm": 1.92, "cloud_cover": 19}, {"timestamp": "2026-06-11T22:04:28.945850+00:00", "station_id": "GDN_01", "temperature": 15.13, "humidity": 87.68, "pressure": 1025.8, "wind_speed": 3.9, "wind_direction": 227, "rain_mm": 0.85, "cloud_cover": 14}, {"timestamp": "2026-06-11T21:54:28.945850+00:00", "station_id": "GDN_01", "temperature": 13.38, "humidity": 75.8, "pressure": 1012.41, "wind_speed": 5.45, "wind_direction": 320, "rain_mm": 0, "cloud_cover": 43}, {"timestamp": "2026-06-11T21:44:28.945850+00:00", "station_id": "GDN_01", "temperature": 19.53, "humidity": 76.6, "pressure": 1017.93, "wind_speed": 13.66, "wind_direction": 212, "rain_mm": 0.46, "cloud_cover": 54}, {"timestamp": "2026-06-11T21:34:28.945850+00:00", "station_id": "GDN_01", "temperature": 14.82, "humidity": 65.94, "pressure": 999.82, "wind_speed": 6.43, "wind_direction": 212, "rain_mm": 0.44, "cloud_cover": 97}, {"timestamp": "2026-06-11T21:24:28.945850+00:00", "station_id": "GDN_01", "temperature": 15.4, "humidity": 91.19, "pressure": 1000.0, "wind_speed": 5.11, "wind_direction": 293, "rain_mm": 0.29, "cloud_cover": 41}, {"timestamp": "2026-06-11T21:14:28.945850+00:00", "station_id": "GDN_01", "temperature": 15.51, "humidity": 83.64, "pressure": 995.91, "wind_speed": 11.95, "wind_direction": 64, "rain_mm": 0.73, "cloud_cover": 13}, {"timestamp": "2026-06-11T21:04:28.945850+00:00", "station_id": "GDN_01", "temperature": 15.37, "humidity": 85.74, "pressure": 1000.82, "wind_speed": 6.65, "wind_direction": 198, "rain_mm": 0.86, "cloud_cover": 68}, {"timestamp": "2026-06-11T20:54:28.945850+00:00", "station_id": "GDN_01", "temperature": 13.23, "humidity": 80.52, "pressure": 1023.61, "wind_speed": 3.62, "wind_direction": 147, "rain_mm": 1.27, "cloud_cover": 0}, {"timestamp": "2026-06-11T20:44:28.945850+00:00", "station_id": "GDN_01", "temperature": 19.98, "humidity": 94.08, "pressure": 1003.21, "wind_speed": 11.92, "wind_direction": 58, "rain_mm": 0, "cloud_cover": 72}, {"timestamp": "2026-06-11T20:34:28.945850+00:00", "station_id": "GDN_01", "temperature": 15.37, "humidity": 75.57, "pressure": 1026.03, "wind_speed": 7.49, "wind_direction": 33, "rain_mm": 0.43, "cloud_cover": 67}, {"timestamp": "2026-06-11T20:24:28.945850+00:00", "station_id": "GDN_01", "temperature": 17.34, "humidity": 64.33, "pressure": 1008.93, "wind_speed": 2.01, "wind_direction": 41, "rain_mm": 0, "cloud_cover": 90}, {"timestamp": "2026-06-11T20:14:28.945850+00:00", "station_id": "GDN_01", "temperature": 13.21, "humidity": 84.53, "pressure": 1021.0, "wind_speed": 6.84, "wind_direction": 260, "rain_mm": 0.64, "cloud_cover": 42}, {"timestamp": "2026-06-11T20:04:28.945850+00:00", "station_id": "GDN_01", "temperature": 19.61, "humidity": 67.99, "pressure": 1005.13, "wind_speed": 7.08, "wind_direction": 3, "rain_mm": 0.94, "cloud_cover": 55}, {"timestamp": "2026-06-11T19:54:28.945850+00:00", "station_id": "GDN_01", "temperature": 19.74, "humidity": 93.04, "pressure": 1006.0, "wind_speed": 2.58, "wind_direction": 13, "rain_mm": 0, "cloud_cover": 33}, {"timestamp": "2026-06-11T19:44:28.945850+00:00", "station_id": "GDN_01", "temperature": 13.55, "humidity": 46.56, "pressure": 1019.56, "wind_speed": 12.96, "wind_direction": 39, "rain_mm": 1.55, "cloud_cover": 49}, {"timestamp": "2026-06-11T19:34:28.945850+00:00", "station_id": "GDN_01", "temperature": 13.71, "humidity": 80.37, "pressure": 1008.51, "wind_speed": 13.37, "wind_direction": 297, "rain_mm": 2.58, "cloud_cover": 8}, {"timestamp": "2026-06-11T19:24:28.945850+00:00", "station_id": "GDN_01", "temperature": 19.48, "humidity": 54.23, "pressure": 1006.36, "wind_speed": 3.06, "wind_direction": 344, "rain_mm": 0.58, "cloud_cover": 96}, {"timestamp": "2026-06-11T19:14:28.945850+00:00", "station_id": "GDN_01", "temperature": 14.42, "humidity": 52.54, "pressure": 1011.99, "wind_speed": 9.97, "wind_direction": 179, "rain_mm": 0, "cloud_cover": 27}, {"timestamp": "2026-06-11T19:04:28.945850+00:00", "station_id": "GDN_01", "temperature": 16.45, "humidity": 75.83, "pressure": 1008.52, "wind_speed": 13.39, "wind_direction": 214, "rain_mm": 0.48, "cloud_cover": 76}, {"timestamp": "2026-06-11T18:54:28.945850+00:00", "station_id": "GDN_01", "temperature": 17.63, "humidity": 71.24, "pressure": 1023.55, "wind_speed": 4.46, "wind_direction": 7, "rain_mm": 0.89, "cloud_cover": 55}, {"timestamp": "2026-06-11T18:44:28.945850+00:00", "station_id": "GDN_01", "temperature": 18.68, "humidity": 64.27, "pressure": 1022.91, "wind_speed": 0.35, "wind_direction": 16, "rain_mm": 0.33, "cloud_cover": 30}, {"timestamp": "2026-06-11T18:34:28.945850+00:00", "station_id": "GDN_01", "temperature": 19.61, "humidity": 49.05, "pressure": 1001.4, "wind_speed": 2.34, "wind_direction": 53, "rain_mm": 0.21, "cloud_cover": 79}, {"timestamp": "2026-06-11T18:24:28.945850+00:00", "station_id": "GDN_01", "temperature": 17.91, "humidity": 75.63, "pressure": 1017.8, "wind_speed": 11.72, "wind_direction": 354, "rain_mm": 0, "cloud_cover": 52}, {"timestamp": "2026-06-11T18:14:28.945850+00:00", "station_id": "GDN_01", "temperature": 14.02, "humidity": 60.04, "pressure": 1027.25, "wind_speed": 11.0, "wind_direction": 290, "rain_mm": 0.39, "cloud_cover": 47}, {"timestamp": "2026-06-11T18:04:28.945850+00:00", "station_id": "GDN_01", "temperature": 20.54, "humidity": 48.01, "pressure": 1027.47, "wind_speed": 9.2, "wind_direction": 137, "rain_mm": 1.6, "cloud_cover": 59}, {"timestamp": "2026-06-11T17:54:28.945850+00:00", "station_id": "GDN_01", "temperature": 16.32, "humidity": 92.32, "pressure": 1007.98, "wind_speed": 7.2, "wind_direction": 286, "rain_mm": 1.91, "cloud_cover": 19}, {"timestamp": "2026-06-11T17:44:28.945850+00:00", "station_id": "GDN_01", "temperature": 15.24, "humidity": 59.61, "pressure": 1029.01, "wind_speed": 10.76, "wind_direction": 197, "rain_mm": 0, "cloud_cover": 36}, {"timestamp": "2026-06-11T17:34:28.945850+00:00", "station_id": "GDN_01", "temperature": 17.94, "humidity": 57.91, "pressure": 1009.01, "wind_speed": 11.58, "wind_direction": 95, "rain_mm": 1.09, "cloud_cover": 94}, {"timestamp": "2026-06-11T17:24:28.945850+00:00", "station_id": "GDN_01", "temperature": 13.6, "humidity": 49.78, "pressure": 1022.88, "wind_speed": 6.63, "wind_direction": 117, "rain_mm": 0, "cloud_cover": 33}, {"timestamp": "2026-06-11T17:14:28.945850+00:00", "station_id": "GDN_01", "temperature": 19.91, "humidity": 79.42, "pressure": 1012.09, "wind_speed": 3.86, "wind_direction": 40, "rain_mm": 0, "cloud_cover": 62}, {"timestamp": "2026-06-11T17:04:28.945850+00:00", "station_id": "GDN_01", "temperature": 13.35, "humidity": 60.27, "pressure": 1020.22, "wind_speed": 1.59, "wind_direction": 343, "rain_mm": 0.65, "cloud_cover": 35}, {"timestamp": "2026-06-11T16:54:28.945850+00:00", "station_id": "GDN_01", "temperature": 19.97, "humidity": 61.1, "pressure": 998.61, "wind_speed": 5.42, "wind_direction": 111, "rain_mm": 0, "cloud_cover": 30}, {"timestamp": "2026-06-11T16:44:28.945850+00:00", "station_id": "GDN_01", "temperature": 19.21, "humidity": 91.71, "pressure": 1007.93, "wind_speed": 1.84, "wind_direction": 34, "rain_mm": 0.06, "cloud_cover": 22}, {"timestamp": "2026-06-11T16:34:28.945850+00:00", "station_id": "GDN_01", "temperature": 17.21, "humidity": 51.28, "pressure": 1004.85, "wind_speed": 12.25, "wind_direction": 266, "rain_mm": 2.05, "cloud_cover": 21}, {"timestamp": "2026-06-11T16:24:28.945850+00:00", "station_id": "GDN_01", "temperature": 18.23, "humidity": 68.3, "pressure": 997.79, "wind_speed": 0.05, "wind_direction": 163, "rain_mm": 0, "cloud_cover": 86}, {"timestamp": "2026-06-11T16:14:28.945850+00:00", "station_id": "GDN_01", "temperature": 18.45, "humidity": 51.64, "pressure": 1020.58, "wind_speed": 13.13, "wind_direction": 145, "rain_mm": 0.14, "cloud_cover": 46}, {"timestamp": "2026-06-11T16:04:28.945850+00:00", "station_id": "GDN_01", "temperature": 19.07, "humidity": 87.59, "pressure": 1002.92, "wind_speed": 2.4, "wind_direction": 339, "rain_mm": 0.97, "cloud_cover": 25}, {"timestamp": "2026-06-11T15:54:28.945850+00:00", "station_id": "GDN_01", "temperature": 19.88, "humidity": 63.52, "pressure": 1001.5, "wind_speed": 9.32, "wind_direction": 224, "rain_mm": 1.46, "cloud_cover": 20}, {"timestamp": "2026-06-11T15:44:28.945850+00:00", "station_id": "GDN_01", "temperature": 16.51, "humidity": 79.84, "pressure": 1018.23, "wind_speed": 13.74, "wind_direction": 293, "rain_mm": 0.31, "cloud_cover": 100}, {"timestamp": "2026-06-11T15:34:28.945850+00:00", "station_id": "GDN_01", "temperature": 14.06, "humidity": 84.91, "pressure": 1010.55, "wind_speed": 1.83, "wind_direction": 170, "rain_mm": 0, "cloud_cover": 70}, {"timestamp": "2026-06-11T15:24:28.945850+00:00", "station_id": "GDN_01", "temperature": 17.67, "humidity": 92.35, "pressure": 1021.17, "wind_speed": 3.24, "wind_direction": 352, "rain_mm": 0.38, "cloud_cover": 41}, {"timestamp": "2026-06-11T15:14:28.945850+00:00", "station_id": "GDN_01", "temperature": 18.53, "humidity": 58.85, "pressure": 1018.9, "wind_speed": 6.81, "wind_direction": 157, "rain_mm": 1.33, "cloud_cover": 58}, {"timestamp": "2026-06-11T15:04:28.945850+00:00", "station_id": "GDN_01", "temperature": 18.41, "humidity": 71.2, "pressure": 1027.3, "wind_speed": 4.49, "wind_direction": 323, "rain_mm": 0.66, "cloud_cover": 66}, {"timestamp": "2026-06-11T14:54:28.945850+00:00", "station_id": "GDN_01", "temperature": 18.21, "humidity": 79.09, "pressure": 1006.35, "wind_speed": 8.29, "wind_direction": 15, "rain_mm": 0, "cloud_cover": 94}, {"timestamp": "2026-06-11T14:44:28.945850+00:00", "station_id": "GDN_01", "temperature": 14.09, "humidity": 82.93, "pressure": 1029.89, "wind_speed": 13.86, "wind_direction": 137, "rain_mm": 0, "cloud_cover": 57}, {"timestamp": "2026-06-11T14:34:28.945850+00:00", "station_id": "GDN_01", "temperature": 15.83, "humidity": 86.59, "pressure": 1025.29, "wind_speed": 2.41, "wind_direction": 76, "rain_mm": 0, "cloud_cover": 55}, {"timestamp": "2026-06-11T14:24:28.945850+00:00", "station_id": "GDN_01", "temperature": 14.17, "humidity": 91.31, "pressure": 1008.18, "wind_speed": 13.26, "wind_direction": 248, "rain_mm": 0, "cloud_cover": 10}, {"timestamp": "2026-06-11T14:14:28.945850+00:00", "station_id": "GDN_01", "temperature": 19.79, "humidity": 85.14, "pressure": 1017.29, "wind_speed": 1.37, "wind_direction": 181, "rain_mm": 0.06, "cloud_cover": 60}, {"timestamp": "2026-06-11T14:04:28.945850+00:00", "station_id": "GDN_01", "temperature": 13.19, "humidity": 52.03, "pressure": 995.49, "wind_speed": 11.11, "wind_direction": 42, "rain_mm": 0.32, "cloud_cover": 50}, {"timestamp": "2026-06-11T13:54:28.945850+00:00", "station_id": "GDN_01", "temperature": 13.18, "humidity": 91.25, "pressure": 1012.61, "wind_speed": 2.11, "wind_direction": 83, "rain_mm": 0, "cloud_cover": 66}, {"timestamp": "2026-06-11T13:44:28.945850+00:00", "station_id": "GDN_01", "temperature": 15.81, "humidity": 77.76, "pressure": 1024.23, "wind_speed": 12.99, "wind_direction": 191, "rain_mm": 0, "cloud_cover": 27}, {"timestamp": "2026-06-11T13:34:28.945850+00:00", "station_id": "GDN_01", "temperature": 17.03, "humidity": 56.89, "pressure": 1013.89, "wind_speed": 11.35, "wind_direction": 306, "rain_mm": 0.59, "cloud_cover": 37}, {"timestamp": "2026-06-11T13:24:28.945850+00:00", "station_id": "GDN_01", "temperature": 20.88, "humidity": 73.16, "pressure": 1026.37, "wind_speed": 7.01, "wind_direction": 281, "rain_mm": 1.24, "cloud_cover": 70}, {"timestamp": "2026-06-11T13:14:28.945850+00:00", "station_id": "GDN_01", "temperature": 13.2, "humidity": 64.66, "pressure": 995.99, "wind_speed": 9.81, "wind_direction": 25, "rain_mm": 0, "cloud_cover": 64}, {"timestamp": "2026-06-11T13:04:28.945850+00:00", "station_id": "GDN_01", "temperature": 15.81, "humidity": 69.57, "pressure": 998.23, "wind_speed": 12.22, "wind_direction": 260, "rain_mm": 0, "cloud_cover": 41}, {"timestamp": "2026-06-11T12:54:28.945850+00:00", "station_id": "GDN_01", "temperature": 17.04, "humidity": 75.23, "pressure": 1027.77, "wind_speed": 7.44, "wind_direction": 345, "rain_mm": 1.3, "cloud_cover": 48}, {"timestamp": "2026-06-11T12:44:28.945850+00:00", "station_id": "GDN_01", "temperature": 18.86, "humidity": 85.54, "pressure": 1007.47, "wind_speed": 10.41, "wind_direction": 64, "rain_mm": 1.72, "cloud_cover": 47}, {"timestamp": "2026-06-11T12:34:28.945850+00:00", "station_id": "GDN_01", "temperature": 20.96, "humidity": 47.24, "pressure": 1013.89, "wind_speed": 2.09, "wind_direction": 298, "rain_mm": 0, "cloud_cover": 90}, {"timestamp": "2026-06-11T12:24:28.945850+00:00", "station_id": "GDN_01", "temperature": 13.59, "humidity": 87.63, "pressure": 1014.09, "wind_speed": 10.99, "wind_direction": 83, "rain_mm": 0, "cloud_cover": 58}, {"timestamp": "2026-06-11T12:14:28.945850+00:00", "station_id": "GDN_01", "temperature": 19.85, "humidity": 88.22, "pressure": 1021.55, "wind_speed": 8.54, "wind_direction": 274, "rain_mm": 0.14, "cloud_cover": 84}, {"timestamp": "2026-06-11T12:04:28.945850+00:00", "station_id": "GDN_01", "temperature": 18.08, "humidity": 94.45, "pressure": 1021.66, "wind_speed": 9.87, "wind_direction": 143, "rain_mm": 0.37, "cloud_cover": 74}, {"timestamp": "2026-06-11T11:54:28.945850+00:00", "station_id": "GDN_01", "temperature": 20.83, "humidity": 79.46, "pressure": 1011.12, "wind_speed": 10.77, "wind_direction": 331, "rain_mm": 0, "cloud_cover": 93}, {"timestamp": "2026-06-11T11:44:28.945850+00:00", "station_id": "GDN_01", "temperature": 17.94, "humidity": 89.01, "pressure": 1011.46, "wind_speed": 5.11, "wind_direction": 204, "rain_mm": 1.18, "cloud_cover": 5}, {"timestamp": "2026-06-11T11:34:28.945850+00:00", "station_id": "GDN_01", "temperature": 13.93, "humidity": 76.77, "pressure": 1006.74, "wind_speed": 8.92, "wind_direction": 64, "rain_mm": 0.78, "cloud_cover": 43}, {"timestamp": "2026-06-11T11:24:28.945850+00:00", "station_id": "GDN_01", "temperature": 15.08, "humidity": 77.75, "pressure": 1020.47, "wind_speed": 8.12, "wind_direction": 112, "rain_mm": 0, "cloud_cover": 14}, {"timestamp": "2026-06-11T11:14:28.945850+00:00", "station_id": "GDN_01", "temperature": 20.35, "humidity": 66.32, "pressure": 1029.45, "wind_speed": 4.82, "wind_direction": 91, "rain_mm": 1.34, "cloud_cover": 61}, {"timestamp": "2026-06-11T11:04:28.945850+00:00", "station_id": "GDN_01", "temperature": 18.96, "humidity": 66.58, "pressure": 1006.32, "wind_speed": 11.73, "wind_direction": 245, "rain_mm": 0, "cloud_cover": 73}, {"timestamp": "2026-06-11T10:54:28.945850+00:00", "station_id": "GDN_01", "temperature": 13.08, "humidity": 79.83, "pressure": 1028.57, "wind_speed": 6.68, "wind_direction": 318, "rain_mm": 0.19, "cloud_cover": 5}, {"timestamp": "2026-06-11T10:44:28.945850+00:00", "station_id": "GDN_01", "temperature": 14.18, "humidity": 78.56, "pressure": 1005.22, "wind_speed": 7.9, "wind_direction": 161, "rain_mm": 0, "cloud_cover": 38}, {"timestamp": "2026-06-11T10:34:28.945850+00:00", "station_id": "GDN_01", "temperature": 19.09, "humidity": 66.6, "pressure": 1001.91, "wind_speed": 0.6, "wind_direction": 121, "rain_mm": 1.4, "cloud_cover": 4}, {"timestamp": "2026-06-11T10:24:28.945850+00:00", "station_id": "GDN_01", "temperature": 19.6, "humidity": 82.71, "pressure": 1015.4, "wind_speed": 10.8, "wind_direction": 18, "rain_mm": 0.03, "cloud_cover": 45}, {"timestamp": "2026-06-11T10:14:28.945850+00:00", "station_id": "GDN_01", "temperature": 15.45, "humidity": 65.42, "pressure": 998.08, "wind_speed": 6.13, "wind_direction": 312, "rain_mm": 0, "cloud_cover": 79}, {"timestamp": "2026-06-11T10:04:28.945850+00:00", "station_id": "GDN_01", "temperature": 20.21, "humidity": 62.64, "pressure": 1017.38, "wind_speed": 10.2, "wind_direction": 79, "rain_mm": 0, "cloud_cover": 63}, {"timestamp": "2026-06-11T09:54:28.945850+00:00", "station_id": "GDN_01", "temperature": 17.48, "humidity": 45.69, "pressure": 1015.49, "wind_speed": 1.1, "wind_direction": 151, "rain_mm": 1.09, "cloud_cover": 72}, {"timestamp": "2026-06-11T09:44:28.945850+00:00", "station_id": "GDN_01", "temperature": 15.41, "humidity": 78.01, "pressure": 996.03, "wind_speed": 2.15, "wind_direction": 316, "rain_mm": 0.85, "cloud_cover": 23}, {"timestamp": "2026-06-11T09:34:28.945850+00:00", "station_id": "GDN_01", "temperature": 13.84, "humidity": 71.73, "pressure": 1003.25, "wind_speed": 7.19, "wind_direction": 261, "rain_mm": 0.56, "cloud_cover": 36}, {"timestamp": "2026-06-11T09:24:28.945850+00:00", "station_id": "GDN_01", "temperature": 15.34, "humidity": 71.06, "pressure": 996.55, "wind_speed": 11.51, "wind_direction": 206, "rain_mm": 0.15, "cloud_cover": 14}, {"timestamp": "2026-06-11T09:14:28.945850+00:00", "station_id": "GDN_01", "temperature": 16.95, "humidity": 75.07, "pressure": 1010.71, "wind_speed": 2.68, "wind_direction": 221, "rain_mm": 0, "cloud_cover": 37}, {"timestamp": "2026-06-11T09:04:28.945850+00:00", "station_id": "GDN_01", "temperature": 18.73, "humidity": 48.4, "pressure": 1029.27, "wind_speed": 10.66, "wind_direction": 244, "rain_mm": 0, "cloud_cover": 73}, {"timestamp": "2026-06-11T08:54:28.945850+00:00", "station_id": "GDN_01", "temperature": 14.86, "humidity": 83.04, "pressure": 1018.28, "wind_speed": 3.66, "wind_direction": 335, "rain_mm": 0.04, "cloud_cover": 4}, {"timestamp": "2026-06-11T08:44:28.945850+00:00", "station_id": "GDN_01", "temperature": 19.11, "humidity": 89.26, "pressure": 1022.6, "wind_speed": 1.67, "wind_direction": 277, "rain_mm": 0, "cloud_cover": 4}, {"timestamp": "2026-06-11T08:34:28.945850+00:00", "station_id": "GDN_01", "temperature": 19.56, "humidity": 71.69, "pressure": 999.53, "wind_speed": 8.59, "wind_direction": 151, "rain_mm": 0.87, "cloud_cover": 87}, {"timestamp": "2026-06-11T08:24:28.945850+00:00", "station_id": "GDN_01", "temperature": 13.99, "humidity": 85.89, "pressure": 1012.25, "wind_speed": 10.21, "wind_direction": 332, "rain_mm": 0, "cloud_cover": 64}, {"timestamp": "2026-06-11T08:14:28.945850+00:00", "station_id": "GDN_01", "temperature": 18.96, "humidity": 63.7, "pressure": 997.72, "wind_speed": 9.04, "wind_direction": 155, "rain_mm": 0.77, "cloud_cover": 50}, {"timestamp": "2026-06-11T08:04:28.945850+00:00", "station_id": "GDN_01", "temperature": 20.11, "humidity": 82.9, "pressure": 1021.82, "wind_speed": 7.44, "wind_direction": 118, "rain_mm": 1.96, "cloud_cover": 45}, {"timestamp": "2026-06-11T07:54:28.945850+00:00", "station_id": "GDN_01", "temperature": 17.89, "humidity": 77.15, "pressure": 1016.66, "wind_speed": 6.56, "wind_direction": 306, "rain_mm": 0, "cloud_cover": 34}, {"timestamp": "2026-06-11T07:44:28.945850+00:00", "station_id": "GDN_01", "temperature": 19.48, "humidity": 74.85, "pressure": 1015.22, "wind_speed": 13.43, "wind_direction": 113, "rain_mm": 0.25, "cloud_cover": 42}, {"timestamp": "2026-06-11T07:34:28.945850+00:00", "station_id": "GDN_01", "temperature": 14.55, "humidity": 73.68, "pressure": 1007.9, "wind_speed": 3.85, "wind_direction": 171, "rain_mm": 0.5, "cloud_cover": 92}, {"timestamp": "2026-06-11T07:24:28.945850+00:00", "station_id": "GDN_01", "temperature": 17.18, "humidity": 47.8, "pressure": 1006.35, "wind_speed": 2.97, "wind_direction": 141, "rain_mm": 0.08, "cloud_cover": 73}, {"timestamp": "2026-06-11T07:14:28.945850+00:00", "station_id": "GDN_01", "temperature": 14.14, "humidity": 47.33, "pressure": 1001.9, "wind_speed": 4.09, "wind_direction": 142, "rain_mm": 0.39, "cloud_cover": 95}, {"timestamp": "2026-06-11T07:04:28.945850+00:00", "station_id": "GDN_01", "temperature": 13.74, "humidity": 73.72, "pressure": 1000.92, "wind_speed": 2.92, "wind_direction": 274, "rain_mm": 1.1, "cloud_cover": 17}, {"timestamp": "2026-06-11T06:54:28.945850+00:00", "station_id": "GDN_01", "temperature": 19.37, "humidity": 54.28, "pressure": 1030.0, "wind_speed": 11.09, "wind_direction": 14, "rain_mm": 0.46, "cloud_cover": 29}, {"timestamp": "2026-06-11T06:44:28.945850+00:00", "station_id": "GDN_01", "temperature": 13.19, "humidity": 49.16, "pressure": 1019.85, "wind_speed": 12.45, "wind_direction": 148, "rain_mm": 0, "cloud_cover": 86}, {"timestamp": "2026-06-11T06:34:28.945850+00:00", "station_id": "GDN_01", "temperature": 20.58, "humidity": 59.5, "pressure": 996.88, "wind_speed": 10.79, "wind_direction": 203, "rain_mm": 0.25, "cloud_cover": 48}, {"timestamp": "2026-06-11T06:24:28.945850+00:00", "station_id": "GDN_01", "temperature": 13.45, "humidity": 57.19, "pressure": 1023.94, "wind_speed": 7.06, "wind_direction": 292, "rain_mm": 0, "cloud_cover": 64}, {"timestamp": "2026-06-11T06:14:28.945850+00:00", "station_id": "GDN_01", "temperature": 19.24, "humidity": 61.3, "pressure": 996.74, "wind_speed": 13.06, "wind_direction": 223, "rain_mm": 0.88, "cloud_cover": 34}, {"timestamp": "2026-06-11T06:04:28.945850+00:00", "station_id": "GDN_01", "temperature": 20.73, "humidity": 62.7, "pressure": 1012.85, "wind_speed": 6.53, "wind_direction": 340, "rain_mm": 0, "cloud_cover": 54}, {"timestamp": "2026-06-11T05:54:28.945850+00:00", "station_id": "GDN_01", "temperature": 17.59, "humidity": 47.81, "pressure": 1027.94, "wind_speed": 4.39, "wind_direction": 136, "rain_mm": 0, "cloud_cover": 91}, {"timestamp": "2026-06-11T05:44:28.945850+00:00", "station_id": "GDN_01", "temperature": 15.33, "humidity": 47.96, "pressure": 1014.34, "wind_speed": 2.73, "wind_direction": 70, "rain_mm": 0, "cloud_cover": 31}, {"timestamp": "2026-06-11T05:34:28.945850+00:00", "station_id": "GDN_01", "temperature": 19.98, "humidity": 69.77, "pressure": 1029.77, "wind_speed": 5.17, "wind_direction": 315, "rain_mm": 0, "cloud_cover": 58}, {"timestamp": "2026-06-11T05:24:28.945850+00:00", "station_id": "GDN_01", "temperature": 13.06, "humidity": 91.22, "pressure": 1027.55, "wind_speed": 13.48, "wind_direction": 245, "rain_mm": 0.03, "cloud_cover": 71}, {"timestamp": "2026-06-11T05:14:28.945850+00:00", "station_id": "GDN_01", "temperature": 16.37, "humidity": 61.88, "pressure": 1029.99, "wind_speed": 3.83, "wind_direction": 3, "rain_mm": 0.81, "cloud_cover": 4}, {"timestamp": "2026-06-11T05:04:28.945850+00:00", "station_id": "GDN_01", "temperature": 18.6, "humidity": 51.44, "pressure": 1020.1, "wind_speed": 2.13, "wind_direction": 261, "rain_mm": 1.15, "cloud_cover": 70}, {"timestamp": "2026-06-11T04:54:28.945850+00:00", "station_id": "GDN_01", "temperature": 18.1, "humidity": 87.68, "pressure": 1001.39, "wind_speed": 5.86, "wind_direction": 57, "rain_mm": 3.18, "cloud_cover": 50}, {"timestamp": "2026-06-11T04:44:28.945850+00:00", "station_id": "GDN_01", "temperature": 20.16, "humidity": 59.92, "pressure": 1014.78, "wind_speed": 8.72, "wind_direction": 357, "rain_mm": 0.68, "cloud_cover": 21}]}